{"nodes": [{"url": "https://ja.wikipedia.org/wiki/\u3042\u3051\u306e\u7f8e\u6182", "sentence": "<p><b>\u3042\u3051\u306e \u7f8e\u6182</b>\uff08\u3042\u3051\u306e \u307f\u3086\u3046\u30011970\u5e7410\u670814\u65e5 - \uff09\u306f\u3001\u5343\u8449\u770c\u51fa\u8eab\u306eAV\u5973\u512a\u3002\u8840\u6db2\u578b:A\u578b\u3002\u8eab\u9577:151cm\u3002</p>", "imurl": "N/A", "name": "\u3042\u3051\u306e\u7f8e\u6182", "title": "\u3042\u3051\u306e\u7f8e\u6182"}, {"url": "https://ja.wikipedia.org/wiki/\u68ee\u5ddd\u3044\u3065\u307f", "title": "\u68ee\u5ddd\u3044\u3065\u307f", "name": "info", "sentence": " \u305f\u3081\u3044\u304d I LOVE YOU\u3000\uff087\u670820\u65e5\u3001SEXY COLLECTION\uff09\u2026<span id = 'relation'>\u5171\u6f14</span>\uff1a<span id='person'>\u3042\u3051\u306e\u7f8e\u6182</span>\u30fb\u6e21\u8fba\u5343\u5c0b"}, {"url": "https://ja.wikipedia.org/wiki/\u68ee\u5ddd\u3044\u3065\u307f", "sentence": "<p><b>\u68ee\u5ddd \u3044\u3065\u307f</b>\uff08\u3082\u308a\u304b\u308f \u3044\u3065\u307f\u30011971\u5e745\u670827\u65e5 - \uff09\u306f\u3001\u6771\u4eac\u90fd\u51fa\u8eab\u306e\u5143AV\u5973\u512a\u30fb\u5143\u30b9\u30c8\u30ea\u30c3\u30d1\u30fc\u3002</p>", "imurl": "N/A", "name": "\u68ee\u5ddd\u3044\u3065\u307f", "title": "\u68ee\u5ddd\u3044\u3065\u307f"}], "links": [{"source": 0, "target": 1, "value": 20}, {"source": 1, "target": 2, "value": 20}]}