{"nodes": [{"url": "https://ja.wikipedia.org/wiki/\u30af\u30ea\u30b9\u30bf\u30eb\u30fb\u30d0\u30fc\u30ca\u30fc\u30c9", "sentence": "<p><b>\u30af\u30ea\u30b9\u30bf\u30eb\u30fb\u30d0\u30fc\u30ca\u30fc\u30c9</b>\uff08Crystal Bernard \u30011961\u5e749\u670830\u65e5 - \uff09\u306f\u3001\u30c6\u30ad\u30b5\u30b9\u5dde\u30ac\u30fc\u30e9\u30f3\u30c9\u751f\u307e\u308c\u306e\u7c73\u56fd\u306e\u5973\u512a\u3001\u6b4c\u624b\u3002</p>", "imurl": "N/A", "name": "\u30af\u30ea\u30b9\u30bf\u30eb\u30fb\u30d0\u30fc\u30ca\u30fc\u30c9", "title": "\u30af\u30ea\u30b9\u30bf\u30eb\u30fb\u30d0\u30fc\u30ca\u30fc\u30c9"}, {"url": "https://ja.wikipedia.org/wiki/\u30ec\u30d9\u30c3\u30ab\u30fb\u30b7\u30e3\u30fc\u30eb", "title": "\u30ec\u30d9\u30c3\u30ab\u30fb\u30b7\u30e3\u30fc\u30eb", "name": "info", "sentence": "\u305d\u306e\u756a\u7d44\u3067<span id='person'>\u30b9\u30c6\u30a3\u30fc\u30f4\u30f3\u30fb\u30a6\u30a7\u30d0\u30fc</span>\u3001<span id='person'>\u30c6\u30a3\u30e2\u30b7\u30fc\u30fb\u30c7\u30a4\u30ea\u30fc</span>\u3001<span id='person'>\u30c8\u30fc\u30de\u30b9\u30fb\u30d8\u30a4\u30c7\u30f3\u30fb\u30c1\u30e3\u30fc\u30c1</span>\u3001<span id='person'>\u30af\u30ea\u30b9\u30bf\u30eb\u30fb\u30d0\u30fc\u30ca\u30fc\u30c9</span>\u3068<span id = 'relation'>\u5171\u6f14</span>\u3057\u305f"}, {"url": "https://ja.wikipedia.org/wiki/\u30c8\u30fc\u30de\u30b9\u30fb\u30d8\u30a4\u30c7\u30f3\u30fb\u30c1\u30e3\u30fc\u30c1", "sentence": "<p><b>\u30c8\u30fc\u30de\u30b9\u30fb\u30d8\u30a4\u30c7\u30f3\u30fb\u30c1\u30e3\u30fc\u30c1</b>\uff08<b>Thomas Haden Church</b>, 1960\u5e746\u670817\u65e5 - \uff09\u306f\u3001\u30a2\u30e1\u30ea\u30ab\u5408\u8846\u56fd\u306e\u4ff3\u512a\u3002</p>", "imurl": "N/A", "name": "\u30c8\u30fc\u30de\u30b9\u30fb\u30d8\u30a4\u30c7\u30f3\u30fb\u30c1\u30e3\u30fc\u30c1", "title": "\u30c8\u30fc\u30de\u30b9\u30fb\u30d8\u30a4\u30c7\u30f3\u30fb\u30c1\u30e3\u30fc\u30c1"}, {"url": "https://ja.wikipedia.org/wiki/\u30ec\u30d9\u30c3\u30ab\u30fb\u30b7\u30e3\u30fc\u30eb", "sentence": "<p><b>\u30ec\u30d9\u30c3\u30ab\u30fb\u30b7\u30e3\u30fc\u30eb</b>\uff08Rebecca Schull, 1929\u5e742\u670822\u65e5 - \uff09\u306f\u3001\u30a2\u30e1\u30ea\u30ab\u5408\u8846\u56fd\u51fa\u8eab\u306e\u5973\u512a\u3002</p>", "imurl": "N/A", "name": "\u30ec\u30d9\u30c3\u30ab\u30fb\u30b7\u30e3\u30fc\u30eb", "title": "\u30ec\u30d9\u30c3\u30ab\u30fb\u30b7\u30e3\u30fc\u30eb"}, {"url": "https://ja.wikipedia.org/wiki/\u30b9\u30c6\u30a3\u30fc\u30f4\u30f3\u30fb\u30a6\u30a7\u30d0\u30fc", "sentence": "<p><b>\u30b9\u30c6\u30a3\u30fc\u30f4\u30f3\u30fb\u30a6\u30a7\u30d0\u30fc</b>\uff08Steven Weber, 1961\u5e743\u67084\u65e5 - \uff09\u306f\u3001\u7c73\u56fd\u306e\u4ff3\u512a\u3067\u3042\u308b\u3002</p>", "imurl": "N/A", "name": "\u30b9\u30c6\u30a3\u30fc\u30f4\u30f3\u30fb\u30a6\u30a7\u30d0\u30fc", "title": "\u30b9\u30c6\u30a3\u30fc\u30f4\u30f3\u30fb\u30a6\u30a7\u30d0\u30fc"}, {"url": "https://ja.wikipedia.org/wiki/\u30c6\u30a3\u30e2\u30b7\u30fc\u30fb\u30c7\u30a4\u30ea\u30fc", "sentence": "<p><b>\u30c6\u30a3\u30e2\u30b7\u30fc\u30fb\u30c7\u30a4\u30ea\u30fc</b>\uff08Timothy Daly\u30011956\u5e743\u67081\u65e5 - \uff09\u306f\u3001\u30a2\u30e1\u30ea\u30ab\u5408\u8846\u56fd\u306e\u4ff3\u512a\u3001\u58f0\u512a\u3001\u30d7\u30ed\u30c7\u30e5\u30fc\u30b5\u30fc\u3002</p>", "imurl": "N/A", "name": "\u30c6\u30a3\u30e2\u30b7\u30fc\u30fb\u30c7\u30a4\u30ea\u30fc", "title": "\u30c6\u30a3\u30e2\u30b7\u30fc\u30fb\u30c7\u30a4\u30ea\u30fc"}], "links": [{"source": 0, "target": 1, "value": 20}, {"source": 1, "target": 2, "value": 20}, {"source": 1, "target": 3, "value": 20}, {"source": 1, "target": 4, "value": 20}, {"source": 1, "target": 5, "value": 20}]}