{"nodes": [{"url": "https://ja.wikipedia.org/wiki/\u30b8\u30a7\u30ec\u30df\u30fc\u30fb\u30a2\u30a4\u30a2\u30f3\u30ba", "sentence": "<p><b>\u30b8\u30a7\u30ec\u30df\u30fc\u30fb\u30a2\u30a4\u30a2\u30f3\u30ba</b>\uff08<b>Jeremy Irons</b>, 1948\u5e749\u670819\u65e5 - \uff09\u306f\u3001\u30a4\u30ae\u30ea\u30b9\u306e\u4ff3\u512a\u3002</p>", "imurl": "N/A", "name": "\u30b8\u30a7\u30ec\u30df\u30fc\u30fb\u30a2\u30a4\u30a2\u30f3\u30ba", "title": "\u30b8\u30a7\u30ec\u30df\u30fc\u30fb\u30a2\u30a4\u30a2\u30f3\u30ba"}, {"url": "https://ja.wikipedia.org/wiki/\u30a8\u30ea\u30b6\u30d9\u30b91\u4e16 \u301c\u611b\u3068\u9670\u8b00\u306e\u738b\u5bae\u301c", "title": "\u30a8\u30ea\u30b6\u30d9\u30b91\u4e16 \u301c\u611b\u3068\u9670\u8b00\u306e\u738b\u5bae\u301c", "name": "info", "sentence": "<span id = 'relation'>\u5171\u6f14</span>\u306b<span id='person'>\u30b8\u30a7\u30ec\u30df\u30fc\u30fb\u30a2\u30a4\u30a2\u30f3\u30ba</span>\u3001<span id='person'>\u30d2\u30e5\u30fc\u30fb\u30c0\u30f3\u30b7\u30fc</span>\u4ed6"}, {"url": "https://ja.wikipedia.org/wiki/\u30d2\u30e5\u30fc\u30fb\u30c0\u30f3\u30b7\u30fc", "sentence": "<p><b>\u30d2\u30e5\u30fc\u30fb\u30c0\u30f3\u30b7\u30fc</b>\uff08<b>Hugh Dancy</b>\u30011975\u5e746\u670819\u65e5 - \uff09\u306f\u3001\u30a4\u30ae\u30ea\u30b9\u306e\u4ff3\u512a\u3002</p>", "imurl": "N/A", "name": "\u30d2\u30e5\u30fc\u30fb\u30c0\u30f3\u30b7\u30fc", "title": "\u30d2\u30e5\u30fc\u30fb\u30c0\u30f3\u30b7\u30fc"}], "links": [{"source": 0, "target": 1, "value": 20}, {"source": 1, "target": 2, "value": 20}]}