{"nodes": [{"url": "https://ja.wikipedia.org/wiki/\u30cb\u30fc\u30eb\u30fb\u30d1\u30c8\u30ea\u30c3\u30af\u30fb\u30cf\u30ea\u30b9", "sentence": "<p><b>\u30cb\u30fc\u30eb\u30fb\u30d1\u30c8\u30ea\u30c3\u30af\u30fb\u30cf\u30ea\u30b9</b>\uff08<b>Neil Patrick Harris</b>, 1973\u5e746\u670815\u65e5\u2010 \uff09\u306f\u3001\u30a2\u30e1\u30ea\u30ab\u5408\u8846\u56fd\u30cb\u30e5\u30fc\u30e1\u30ad\u30b7\u30b3\u5dde\u30a2\u30eb\u30d0\u30ab\u30fc\u30ad\u51fa\u8eab\u306e\u4ff3\u512a\u3002</p>", "imurl": "N/A", "name": "\u30cb\u30fc\u30eb\u30fb\u30d1\u30c8\u30ea\u30c3\u30af\u30fb\u30cf\u30ea\u30b9", "title": "\u30cb\u30fc\u30eb\u30fb\u30d1\u30c8\u30ea\u30c3\u30af\u30fb\u30cf\u30ea\u30b9"}, {"url": "https://ja.wikipedia.org/wiki/\u30cb\u30fc\u30eb\u30fb\u30d1\u30c8\u30ea\u30c3\u30af\u30fb\u30cf\u30ea\u30b9", "title": "\u30cb\u30fc\u30eb\u30fb\u30d1\u30c8\u30ea\u30c3\u30af\u30fb\u30cf\u30ea\u30b9", "name": "info", "sentence": "1988\u5e74\u306b<span id='person'>\u30a6\u30fc\u30d4\u30fc\u30fb\u30b4\u30fc\u30eb\u30c9\u30d0\u30fc\u30b0</span>\u3068<span id = 'relation'>\u5171\u6f14</span>\u3057\u305f\u6620\u753b\u300eClara's Heart\u300f\u3067\u30b4\u30fc\u30eb\u30c7\u30f3\u30fb\u30b0\u30ed\u30fc\u30d6\u8cde\u306b\u30ce\u30df\u30cd\u30fc\u30c8\u3055\u308c\u3001\u3055\u3089\u306b\u305d\u306e\u5f8c\u4e3b\u6f14\u3057\u305f\u300e\u5929\u624d\u5c11\u5e74\u30c9\u30ae\u30fc\u30fb\u30cf\u30a6\u30b6\u30fc\u300f\u3067\u3082\u518d\u3073\u30ce\u30df\u30cd\u30fc\u30c8\u3055\u308c\u305f"}, {"url": "https://ja.wikipedia.org/wiki/\u30a6\u30fc\u30d4\u30fc\u30fb\u30b4\u30fc\u30eb\u30c9\u30d0\u30fc\u30b0", "sentence": "<p><b>\u30a6\u30fc\u30d4\u30fc\u30fb\u30b4\u30fc\u30eb\u30c9\u30d0\u30fc\u30b0</b>\uff08<b>Whoopi Goldberg</b>, \u672c\u540d: Caryn Elaine Johnson, 1955\u5e7411\u670813\u65e5 - \uff09\u306f\u3001\u30a2\u30e1\u30ea\u30ab\u5408\u8846\u56fd\u30cb\u30e5\u30fc\u30e8\u30fc\u30af\u51fa\u8eab\u306e\u5973\u512a\u3001\u30b3\u30e1\u30c7\u30a3\u30a8\u30f3\u30cc\u3001\u6b4c\u624b\u3002</p>", "imurl": "N/A", "name": "\u30a6\u30fc\u30d4\u30fc\u30fb\u30b4\u30fc\u30eb\u30c9\u30d0\u30fc\u30b0", "title": "\u30a6\u30fc\u30d4\u30fc\u30fb\u30b4\u30fc\u30eb\u30c9\u30d0\u30fc\u30b0"}, {"url": "https://ja.wikipedia.org/wiki/\u30f4\u30a1\u30cd\u30c3\u30b5\u30fb\u30cf\u30b8\u30a7\u30f3\u30ba", "title": "\u30f4\u30a1\u30cd\u30c3\u30b5\u30fb\u30cf\u30b8\u30a7\u30f3\u30ba", "name": "info", "sentence": "<span id = 'relation'>\u5171\u6f14</span>\u306f\u30b3\u30e1\u30c7\u30a3\u30c9\u30e9\u30de\u300e\u30de\u30de\u3068\u604b\u306b\u843d\u3061\u308b\u307e\u3067\u300f\u306b\u51fa\u6f14\u306e<span id='person'>\u30cb\u30fc\u30eb\u30fb\u30d1\u30c8\u30ea\u30c3\u30af\u30fb\u30cf\u30ea\u30b9</span>\u3067\u672c\u4f5c\u54c1\u306f\u65e5\u672c\u30672012\u5e742\u67084\u65e5\u304b\u3089\u5287\u5834\u516c\u958b\u3055\u308c\u305f<ref></ref>"}, {"url": "https://ja.wikipedia.org/wiki/\u30f4\u30a1\u30cd\u30c3\u30b5\u30fb\u30cf\u30b8\u30a7\u30f3\u30ba", "sentence": "<p><b>\u30f4\u30a1\u30cd\u30c3\u30b5\u30fb\u30a2\u30f3\u30fb\u30cf\u30b8\u30a7\u30f3\u30ba</b>\uff08<b>Vanessa Anne Hudgens</b>\u30011988\u5e7412\u670814\u65e5 - \uff09\u306f\u3001\u30a2\u30e1\u30ea\u30ab\u5408\u8846\u56fd\u306e\u5973\u512a\u3001\u6b4c\u624b\u3001\u30a2\u30a4\u30c9\u30eb\u3002\u8eab\u9577157cm\u3002</p>", "imurl": "N/A", "name": "\u30f4\u30a1\u30cd\u30c3\u30b5\u30fb\u30cf\u30b8\u30a7\u30f3\u30ba", "title": "\u30f4\u30a1\u30cd\u30c3\u30b5\u30fb\u30cf\u30b8\u30a7\u30f3\u30ba"}], "links": [{"source": 0, "target": 1, "value": 20}, {"source": 1, "target": 2, "value": 20}, {"source": 0, "target": 3, "value": 20}, {"source": 3, "target": 4, "value": 20}]}