{"nodes": [{"url": "https://ja.wikipedia.org/wiki/\u30d1\u30a6\u30eb\u30fb\u30d9\u30eb\u30ca\u30a4\u30b9", "sentence": "<p><b>\u30d1\u30a6\u30eb\u30fb\u30d9\u30eb\u30ca\u30a4\u30b9</b>\uff08Paul Bernays, 1888\u5e7410\u670817\u65e5 - 1977\u5e749\u670818\u65e5\uff09\u306f\u30b9\u30a4\u30b9\u306e\u6570\u5b66\u8005\u30fb\u8ad6\u7406\u5b66\u8005\u3002</p>", "imurl": "N/A", "name": "\u30d1\u30a6\u30eb\u30fb\u30d9\u30eb\u30ca\u30a4\u30b9", "title": "\u30d1\u30a6\u30eb\u30fb\u30d9\u30eb\u30ca\u30a4\u30b9"}, {"url": "https://ja.wikipedia.org/wiki/\u30d1\u30a6\u30eb\u30fb\u30d9\u30eb\u30ca\u30a4\u30b9", "title": "\u30d1\u30a6\u30eb\u30fb\u30d9\u30eb\u30ca\u30a4\u30b9", "name": "info", "sentence": " Grundlagen der Mathematik, 2 Vol.\uff081934\u5e74 - 1939\u5e74\u3001<span id='person'>\u30c0\u30d5\u30a3\u30c3\u30c8\u30fb\u30d2\u30eb\u30d9\u30eb\u30c8</span>\u3068\u306e<span id = 'relation'>\u5171\u8457</span>\uff09"}, {"url": "https://ja.wikipedia.org/wiki/\u30c0\u30d5\u30a3\u30c3\u30c8\u30fb\u30d2\u30eb\u30d9\u30eb\u30c8", "sentence": "<p><b>\u30c0\u30d5\u30a3\u30c3\u30c8\u30fb\u30d2\u30eb\u30d9\u30eb\u30c8</b>\uff08David Hilbert, 1862\u5e741\u670823\u65e5 - 1943\u5e742\u670814\u65e5\uff09\u306f\u3001\u30c9\u30a4\u30c4\u306e\u6570\u5b66\u8005\u3002\u300c\u73fe\u4ee3\u6570\u5b66\u306e\u7236\u300d\u3068\u547c\u3070\u308c\u308b\u3002\u540d\u306f\u30c0\u30f4\u30a3\u30c9\u3001\u30c0\u30fc\u30d5\u30a3\u30c3\u30c8\u306a\u3069\u3068\u3082\u8868\u8a18\u3055\u308c\u308b\u3002</p>", "imurl": "N/A", "name": "\u30c0\u30d5\u30a3\u30c3\u30c8\u30fb\u30d2\u30eb\u30d9\u30eb\u30c8", "title": "\u30c0\u30d5\u30a3\u30c3\u30c8\u30fb\u30d2\u30eb\u30d9\u30eb\u30c8"}], "links": [{"source": 0, "target": 1, "value": 20}, {"source": 1, "target": 2, "value": 20}]}