{"nodes": [{"url": "https://ja.wikipedia.org/wiki/\u30de\u30cf\u30c6\u30a3\u30fc\u30eb\u30fb\u30d3\u30f3\u30fb\u30e2\u30cf\u30de\u30c9", "sentence": "<p><b>\u30de\u30cf\u30c6\u30a3\u30fc\u30eb\u30fb\u30d3\u30f3\u30fb\u30e2\u30cf\u30de\u30c9</b>\uff08Mahathir bin Mohamad\u30011925\u5e747\u670810\u65e5/12\u670820\u65e5 - \uff09\u306f\u3001\u30de\u30ec\u30fc\u30b7\u30a2\u306e\u653f\u6cbb\u5bb6\u3001\u533b\u5e2b\u3002\u30de\u30ec\u30fc\u30b7\u30a2\u7b2c4\u4ee3\u9996\u76f8\u3002\u30de\u30ec\u30fc\u30b7\u30a2\u306e\u9996\u76f8\u306e\u4e2d\u3067\u306f\u6700\u9577\u306e22\u5e74\u9593\u3092\u52d9\u3081\u305f\u3002</p>", "imurl": "N/A", "name": "\u30de\u30cf\u30c6\u30a3\u30fc\u30eb\u30fb\u30d3\u30f3\u30fb\u30e2\u30cf\u30de\u30c9", "title": "\u30de\u30cf\u30c6\u30a3\u30fc\u30eb\u30fb\u30d3\u30f3\u30fb\u30e2\u30cf\u30de\u30c9"}, {"url": "https://ja.wikipedia.org/wiki/\u30de\u30cf\u30c6\u30a3\u30fc\u30eb\u30fb\u30d3\u30f3\u30fb\u30e2\u30cf\u30de\u30c9", "title": "\u30de\u30cf\u30c6\u30a3\u30fc\u30eb\u30fb\u30d3\u30f3\u30fb\u30e2\u30cf\u30de\u30c9", "name": "info", "sentence": ""}, {"url": "https://ja.wikipedia.org/wiki/\u77f3\u539f\u614e\u592a\u90ce", "sentence": "<p><b>\u77f3\u539f \u614e\u592a\u90ce</b>\uff08\u3044\u3057\u306f\u3089 \u3057\u3093\u305f\u308d\u3046\u3001\u65e7\u5b57\u4f53\uff1a<b>\u77f3\u539f \u613c\u592a\u90ce</b>\u30011932\u5e74 \uff08\u662d\u548c7\u5e74\uff09 9\u670830\u65e5 - \uff09\u306f\u3001\u65e5\u672c\u306e\u653f\u6cbb\u5bb6\u3001\u4f5c\u5bb6\u3002</p>", "imurl": "N/A", "name": "\u77f3\u539f\u614e\u592a\u90ce", "title": "\u77f3\u539f\u614e\u592a\u90ce"}], "links": [{"source": 0, "target": 1, "value": 20}, {"source": 1, "target": 2, "value": 20}]}