{"nodes": [{"url": "https://ja.wikipedia.org/wiki/\u4e8c\u30ce\u5bae\u77e5\u5b50", "sentence": "<p><b>\u4e8c\u30ce\u5bae \u77e5\u5b50</b>\uff08\u306b\u306e\u307f\u3084 \u3068\u3082\u3053\u30011969\u5e745\u670825\u65e5 - \uff09\u306f\u3001\u65e5\u672c\u306e\u6f2b\u753b\u5bb6\u3002\u57fc\u7389\u770c\u79e9\u7236\u90e1\u7686\u91ce\u753a\u51fa\u8eab\u3001\u57fc\u7389\u770c\u5728\u4f4f\u3002\u5973\u6027\u3002</p>", "imurl": "N/A", "name": "\u4e8c\u30ce\u5bae\u77e5\u5b50", "title": "\u4e8c\u30ce\u5bae\u77e5\u5b50"}, {"url": "https://ja.wikipedia.org/wiki/\u5c0f\u7389\u30e6\u30ad", "title": "\u5c0f\u7389\u30e6\u30ad", "name": "info", "sentence": " \u79c1\u306e\u7d50\u5a5a\u5f0f!\uff08<span id='person'>\u304a\u304b\u3056\u304d\u771f\u91cc</span>\u30fb<span id='person'>\u4e8c\u30ce\u5bae\u77e5\u5b50</span>\u307b\u304b\u3068\u306e<span id = 'relation'>\u5171\u8457</span>\u3001\u30a8\u30c3\u30bb\u30a4\uff09"}, {"url": "https://ja.wikipedia.org/wiki/\u304a\u304b\u3056\u304d\u771f\u91cc", "sentence": "<p><b>\u304a\u304b\u3056\u304d \u771f\u91cc</b>\uff08\u304a\u304b\u3056\u304d \u307e\u308a\u3001\u672c\u540d\u30fb\u5ca1\u5d0e \u771f\u91cc\u30011967\u5e746\u670815\u65e5 - \uff09\u306f\u3001\u65e5\u672c\u306e\u6f2b\u753b\u5bb6\u3001\u30a4\u30e9\u30b9\u30c8\u30ec\u30fc\u30bf\u30fc\u3002\u5973\u6027\u3002\u9577\u91ce\u770c\u51fa\u8eab\u3002</p>", "imurl": "N/A", "name": "\u304a\u304b\u3056\u304d\u771f\u91cc", "title": "\u304a\u304b\u3056\u304d\u771f\u91cc"}], "links": [{"source": 0, "target": 1, "value": 20}, {"source": 1, "target": 2, "value": 20}]}