{"nodes": [{"url": "https://ja.wikipedia.org/wiki/\u4f50\u3005\u6728\u548c\u5fb3", "sentence": "<p><b>\u4f50\u3005\u6728 \u548c\u5fb3</b>\uff08\u3055\u3055\u304d \u304b\u305a\u306e\u308a\u30011986\u5e749\u670811\u65e5 - \uff09\u306f\u4ff3\u512a\u3002\u6771\u4eac\u90fd\u51fa\u8eab\u3002\u8840\u6db2\u578b\u306fA\u578b\u3002</p>", "imurl": "N/A", "name": "\u4f50\u3005\u6728\u548c\u5fb3", "title": "\u4f50\u3005\u6728\u548c\u5fb3"}, {"url": "https://ja.wikipedia.org/wiki/\u4f50\u3005\u6728\u548c\u5fb3", "title": "\u4f50\u3005\u6728\u548c\u5fb3", "name": "info", "sentence": ":<span id='person'>\u9577\u6fa4\u307e\u3055\u307f</span>\u3068<span id = 'relation'>\u5171\u6f14</span>"}, {"url": "https://ja.wikipedia.org/wiki/\u9577\u6fa4\u307e\u3055\u307f", "sentence": "<p><b>\u9577\u6fa4 \u307e\u3055\u307f</b>\uff08\u306a\u304c\u3055\u308f \u307e\u3055\u307f\u30011987\u5e746\u67083\u65e5 - \uff09\u306f\u3001\u65e5\u672c\u306e\u5973\u512a\u3002\u672c\u540d\u540c\u3058\u3002\u611b\u79f0\u306f\u3001<b>\u307e\u3042\u3061\u3083\u3093</b>\u3001<b>\u307e\u3063\u3055\u3093</b>\u3001<b>\u304c\u3063\u3055\u30fc\u308f\u30fc</b>\u3002</p>", "imurl": "N/A", "name": "\u9577\u6fa4\u307e\u3055\u307f", "title": "\u9577\u6fa4\u307e\u3055\u307f"}], "links": [{"source": 0, "target": 1, "value": 20}, {"source": 1, "target": 2, "value": 20}]}