{"nodes": [{"url": "https://ja.wikipedia.org/wiki/\u5016\u7530\u307f\u3089\u3044", "sentence": "<p><b>\u5016\u7530 \u307f\u3089\u3044</b>\uff08\u3053\u3046\u3060 \u307f\u3089\u3044\u30011987\u5e7410\u670816\u65e5 - \uff09\u306f\u3001\u65e5\u672c\u306e\u5143AV\u5973\u512a\u3002 \u5927\u962a\u5e9c\u51fa\u8eab\u3002\u5973\u5b50\u6821\u751f\uff5e\u30ae\u30e3\u30eb\u3001OL\u3001\u82e5\u59bb\u3001\u30ec\u30ba\u307e\u3067\u3001\u5e45\u5e83\u3044\u5f79\u67c4\u3092\u3053\u306a\u305b\u308b\u4e8b\u3068\u3001\u95a2\u897f\u5f01\u3067\u4eba\u6c17\u3092\u535a\u3057\u305f\u3002</p>", "imurl": "N/A", "name": "\u5016\u7530\u307f\u3089\u3044", "title": "\u5016\u7530\u307f\u3089\u3044"}, {"url": "https://ja.wikipedia.org/wiki/\u3046\u308b\u307f\u3086\u3046", "title": "\u3046\u308b\u307f\u3086\u3046", "name": "info", "sentence": " \u96c6\u56e3\u5de8\u4e73\u75f4\u5973\uff084\u670819\u65e5 \u30af\u30ed\u30b9\uff09<span id = 'relation'>\u5171\u6f14</span>:<span id='person'>\u4e03\u702c\u3086\u3046\u308a</span>\u3001\u5b89\u897f\u30ab\u30eb\u30e9\u3001<span id='person'>\u5016\u7530\u307f\u3089\u3044</span>\u3001natsuha"}, {"url": "https://ja.wikipedia.org/wiki/\u4e03\u702c\u3086\u3046\u308a", "sentence": "<p><b>\u4e03\u702c \u3086\u3046\u308a</b>\uff08\u306a\u306a\u305b \u3086\u3046\u308a\u30011986\u5e749\u670819\u65e5 - \uff09\u306f\u3001\u6771\u4eac\u90fd\u51fa\u8eab\u306e\u5143AV\u5973\u512a\u3002</p>", "imurl": "N/A", "name": "\u4e03\u702c\u3086\u3046\u308a", "title": "\u4e03\u702c\u3086\u3046\u308a"}, {"url": "https://ja.wikipedia.org/wiki/\u3046\u308b\u307f\u3086\u3046", "sentence": "<p><b>\u3046\u308b\u307f\u3086\u3046</b>\uff081987\u5e745\u670815\u65e5 - \uff09\u306f\u3001\u65e5\u672c\u306eAV\u5973\u512a\u3002</p>", "imurl": "N/A", "name": "\u3046\u308b\u307f\u3086\u3046", "title": "\u3046\u308b\u307f\u3086\u3046"}, {"url": "https://ja.wikipedia.org/wiki/\u4e03\u702c\u3086\u3046\u308a", "title": "\u4e03\u702c\u3086\u3046\u308a", "name": "info", "sentence": " \u96c6\u56e3\u5de8\u4e73\u75f4\u5973\uff084\u670819\u65e5 \u30af\u30ed\u30b9\uff09<span id = 'relation'>\u5171\u6f14</span>:\u5b89\u897f\u30ab\u30eb\u30e9\u3001<span id='person'>\u3046\u308b\u307f\u3086\u3046</span>\u3001<span id='person'>\u5016\u7530\u307f\u3089\u3044</span>\u3001natsuha"}], "links": [{"source": 0, "target": 1, "value": 20}, {"source": 1, "target": 2, "value": 20}, {"source": 1, "target": 3, "value": 20}, {"source": 0, "target": 4, "value": 20}, {"source": 4, "target": 2, "value": 20}, {"source": 4, "target": 3, "value": 20}]}