{"nodes": [{"url": "https://ja.wikipedia.org/wiki/\u53e4\u5c71\u9ad8\u9e97\u96c4", "sentence": "<p><b>\u53e4\u5c71 \u9ad8\u9e97\u96c4</b>\uff08\u3075\u308b\u3084\u307e \u3053\u307e\u304a\u30011920\u5e74\uff08\u5927\u6b639\u5e74\uff098\u67086\u65e5 - 2002\u5e74\uff08\u5e73\u621014\u5e74\uff093\u670811\u65e5\uff09\u306f\u3001\u65e5\u672c\u306e\u5c0f\u8aac\u5bb6\u3001\u968f\u7b46\u5bb6\u3001\u7de8\u96c6\u8005\u3002</p>", "imurl": "N/A", "name": "\u53e4\u5c71\u9ad8\u9e97\u96c4", "title": "\u53e4\u5c71\u9ad8\u9e97\u96c4"}, {"url": "https://ja.wikipedia.org/wiki/\u53e4\u5c71\u9ad8\u9e97\u96c4", "title": "\u53e4\u5c71\u9ad8\u9e97\u96c4", "name": "info", "sentence": ""}, {"url": "https://ja.wikipedia.org/wiki/\u91ce\u5742\u662d\u5982", "sentence": "<p><b>\u91ce\u5742 \u662d\u5982</b>\uff08\u306e\u3055\u304b \u3042\u304d\u3086\u304d\u30011930\u5e74\uff08\u662d\u548c5\u5e74\uff0910\u670810\u65e5 - \uff09\u306f\u65e5\u672c\u306e\u4f5c\u5bb6\u3001\u6b4c\u624b\u3001\u4f5c\u8a5e\u5bb6\u3001\u30bf\u30ec\u30f3\u30c8\u3001\u653f\u6cbb\u5bb6\u3002</p>", "imurl": "N/A", "name": "\u91ce\u5742\u662d\u5982", "title": "\u91ce\u5742\u662d\u5982"}], "links": [{"source": 0, "target": 1, "value": 20}, {"source": 1, "target": 2, "value": 20}]}