{"nodes": [{"url": "https://ja.wikipedia.org/wiki/\u5927\u65e5\u672c\u660e\u6cbb\u88fd\u7cd6", "sentence": "<p><b>\u5927\u65e5\u672c\u660e\u6cbb\u88fd\u7cd6\u682a\u5f0f\u4f1a\u793e</b>\uff08\u3060\u3044\u306b\u3063\u307d\u3093\u3081\u3044\u3058\u305b\u3044\u3068\u3046\uff09\u306f\u3001<b>\u5927\u65e5\u672c\u88fd\u7cd6\u682a\u5f0f\u4f1a\u793e</b>\u3068<b>\u660e\u6cbb\u88fd\u7cd6\u682a\u5f0f\u4f1a\u793e</b>\u304c\u5408\u4f75\u3057\u3066\u767a\u8db3\u3057\u305f\u65e5\u672c\u306e\u88fd\u7cd6\u4f1a\u793e\u3002</p>", "imurl": "https://upload.wikimedia.org/wikipedia/commons/b/b6/Eiichi_Shibusawa_young.jpg", "name": "\u5927\u65e5\u672c\u660e\u6cbb\u88fd\u7cd6", "title": "\u5927\u65e5\u672c\u660e\u6cbb\u88fd\u7cd6"}, {"url": "https://ja.wikipedia.org/wiki/\u65e5\u65b0\u88fd\u7cd6", "title": "\u65e5\u65b0\u88fd\u7cd6", "name": "info", "sentence": "\u95a2\u4fc2\u4f1a\u793e\u306e<span id='entity'>\u65b0\u6771\u65e5\u672c\u88fd\u7cd6</span>\u3092\u901a\u3058\u3066\u3001<span id='entity'>\u4e09\u83f1\u5546\u4e8b</span>\u7cfb\u5217\u30fb\u5927\u624b\u88fd\u7cd6\u4f1a\u793e\u306e<span id='entity'>\u5927\u65e5\u672c\u660e\u6cbb\u88fd\u7cd6</span>\u3068<span id = 'relation'>\u5171\u540c\u751f\u7523</span>\u306e\u63d0\u643a\u3092\u884c\u3063\u3066\u3044\u308b"}, {"url": "https://ja.wikipedia.org/wiki/\u65e5\u65b0\u88fd\u7cd6", "sentence": "<p><b>\u65e5\u65b0\u88fd\u7cd6\u682a\u5f0f\u4f1a\u793e</b>\uff08\u306b\u3063\u3057\u3093\u305b\u3044\u3068\u3046\uff09\u306f\u3001\u7802\u7cd6\u306e\u7cbe\u88fd\u8ca9\u58f2\u3001\u30b9\u30dd\u30fc\u30c4\u30af\u30e9\u30d6\u7d4c\u55b6\u3001\u4e0d\u52d5\u7523\u4e8b\u696d\u3092\u884c\u3046\u65e5\u672c\u306e\u4f01\u696d\u3067\u3042\u308b\u3002</p>", "imurl": "N/A", "name": "\u65e5\u65b0\u88fd\u7cd6", "title": "\u65e5\u65b0\u88fd\u7cd6"}, {"url": "https://ja.wikipedia.org/wiki/\u65b0\u6771\u65e5\u672c\u88fd\u7cd6", "sentence": "<p><b>\u65b0\u6771\u65e5\u672c\u88fd\u7cd6\u682a\u5f0f\u4f1a\u793e</b>\uff08\u3057\u3093\u3072\u304c\u3057\u306b\u307b\u3093\u305b\u3044\u3068\u3046\uff09\u306f\u3001\u7802\u7cd6\u306e\u88fd\u9020\u3092\u884c\u3046\u88fd\u7cd6\u4f1a\u793e\u3002</p>", "imurl": "N/A", "name": "\u65b0\u6771\u65e5\u672c\u88fd\u7cd6", "title": "\u65b0\u6771\u65e5\u672c\u88fd\u7cd6"}, {"url": "https://ja.wikipedia.org/wiki/\u4e09\u83f1\u5546\u4e8b", "sentence": "<p><b>\u4e09\u83f1\u5546\u4e8b\u682a\u5f0f\u4f1a\u793e</b>\uff08\u307f\u3064\u3073\u3057\u3057\u3087\u3046\u3058\u3001\u82f1: <span lang=\"en\" xml:lang=\"en\"><i>Mitsubishi Corporation</i></span>\uff09\u306f\u3001\u4e09\u83f1\u30b0\u30eb\u30fc\u30d7\u306e\u5927\u624b\u7dcf\u5408\u5546\u793e\u3002</p>", "imurl": "N/A", "name": "\u4e09\u83f1\u5546\u4e8b", "title": "\u4e09\u83f1\u5546\u4e8b"}, {"url": "https://ja.wikipedia.org/wiki/\u5927\u65e5\u672c\u660e\u6cbb\u88fd\u7cd6", "title": "\u5927\u65e5\u672c\u660e\u6cbb\u88fd\u7cd6", "name": "info", "sentence": "2001\u5e74\uff08\u5e73\u621013\u5e74\uff09 4\u6708 <span id='entity'>\u65e5\u672c\u751c\u83dc\u88fd\u7cd6</span>\u3068\u95a2\u9580\u88fd\u7cd6\u306b\u304a\u3044\u3066\u7802\u7cd6\u306e<span id = 'relation'>\u5171\u540c\u751f\u7523</span>\u958b\u59cb"}, {"url": "https://ja.wikipedia.org/wiki/\u65e5\u672c\u751c\u83dc\u88fd\u7cd6", "sentence": "<p><b>\u65e5\u672c\u751c\u83dc\u88fd\u7cd6\u682a\u5f0f\u4f1a\u793e</b>\uff08\u306b\u3063\u307d\u3093\u3066\u3093\u3055\u3044\u305b\u3044\u3068\u3046\uff09\u306f\u65e5\u672c\u306e\u88fd\u7cd6\u4f1a\u793e\u3002\u5317\u6d77\u9053\u3092\u751f\u7523\u62e0\u70b9\u3068\u3057\u3066\u88fd\u7cd6\u4e8b\u696d\u3092\u304a\u3053\u306a\u3063\u3066\u3044\u308b\u3002\u7565\u79f0\u306f\u300c<b>\u65e5\u751c</b>\uff08\u306b\u3063\u3066\u3093\uff09\u300d\u307e\u305f\u306f\u300c<b>\u30cb\u30c3\u30c6\u30f3</b>\u300d\u3002</p>", "imurl": "https://upload.wikimedia.org/wikipedia/commons/thumb/e/ec/Beet_museum.JPG/250px-Beet_museum.JPG", "name": "\u65e5\u672c\u751c\u83dc\u88fd\u7cd6", "title": "\u65e5\u672c\u751c\u83dc\u88fd\u7cd6"}, {"url": "https://ja.wikipedia.org/wiki/\u5927\u65e5\u672c\u660e\u6cbb\u88fd\u7cd6", "title": "\u5927\u65e5\u672c\u660e\u6cbb\u88fd\u7cd6", "name": "info", "sentence": "2002\u5e74\uff08\u5e73\u621014\u5e74\uff09 7\u6708 <span id='entity'>\u65e5\u65b0\u88fd\u7cd6</span>\u30fb\u5927\u6771\u88fd\u7cd6\u306e2\u793e\u3068\u65b0\u6771\u65e5\u672c\u88fd\u7cd6\u3067<span id = 'relation'>\u5171\u540c\u751f\u7523</span>\u958b\u59cb"}, {"url": "https://ja.wikipedia.org/wiki/\u5927\u65e5\u672c\u660e\u6cbb\u88fd\u7cd6", "title": "\u5927\u65e5\u672c\u660e\u6cbb\u88fd\u7cd6", "name": "info", "sentence": "2005\u5e74\uff08\u5e73\u621017\u5e74\uff09 10\u6708 <span id='entity'>\u4e2d\u65e5\u672c\u6c37\u7cd6</span>\u682a\u5f0f\u4f1a\u793e\u304c\u95a2\u897f\u88fd\u7cd6\u3067\u306e<span id = 'relation'>\u5171\u540c\u751f\u7523</span>\u306b\u53c2\u52a0"}, {"url": "https://ja.wikipedia.org/wiki/\u4e2d\u65e5\u672c\u6c37\u7cd6", "sentence": "<p><b>\u4e2d\u65e5\u672c\u6c37\u7cd6\u682a\u5f0f\u4f1a\u793e</b>\uff08\u306a\u304b\u306b\u3063\u307d\u3093\u3072\u3087\u3046\u3068\u3046\u3001\u82f1: <span lang=\"en\" xml:lang=\"en\"><i>Naka Nippon Hyoto Co., Ltd.</i></span>\uff09\u306f\u3001\u611b\u77e5\u770c\u540d\u53e4\u5c4b\u5e02\u4e2d\u5ddd\u533a\u306b\u672c\u793e\u3092\u7f6e\u304f\u88fd\u7cd6\u30e1\u30fc\u30ab\u30fc\u3002</p>", "imurl": "https://upload.wikimedia.org/wikipedia/commons/thumb/b/b5/Nakanippon_Hyoto_Headquarter_Office_20141028.JPG/187px-Nakanippon_Hyoto_Headquarter_Office_20141028.JPG", "name": "\u4e2d\u65e5\u672c\u6c37\u7cd6", "title": "\u4e2d\u65e5\u672c\u6c37\u7cd6"}, {"url": "https://ja.wikipedia.org/wiki/\u95a2\u897f\u88fd\u7cd6", "title": "\u95a2\u897f\u88fd\u7cd6", "name": "info", "sentence": "2002\u5e743\u6708\u306b<span id='entity'>\u5869\u6c34\u6e2f\u7cbe\u7cd6</span>\u3001<span id='entity'>\u5927\u65e5\u672c\u660e\u6cbb\u88fd\u7cd6</span>\u3001<span id='entity'>\u5927\u6771\u88fd\u7cd6</span>\u306e3\u793e\u304c\u5869\u6c34\u6e2f\u7cbe\u7cd6\u306e\u5927\u962a\u5de5\u5834\uff08\u5927\u962a\u5e9c\u6cc9\u4f50\u91ce\u5e02\uff09\u3067\u7802\u7cd6\u306e<span id = 'relation'>\u5171\u540c\u751f\u7523</span>\u3092\u884c\u3046\u305f\u3081\u306b\u8a2d\u7acb\u3057\u305f"}, {"url": "https://ja.wikipedia.org/wiki/\u95a2\u897f\u88fd\u7cd6", "sentence": "<p><b>\u95a2\u897f\u88fd\u7cd6\u682a\u5f0f\u4f1a\u793e</b>\uff08\u304b\u3093\u3055\u3044\u305b\u3044\u3068\u3046\uff09\u306f\u3001\u5927\u962a\u5e9c\u6cc9\u4f50\u91ce\u5e02\u306b\u672c\u793e\u3092\u7f6e\u304f\u88fd\u7cd6\u4f1a\u793e\u3002</p>", "imurl": "N/A", "name": "\u95a2\u897f\u88fd\u7cd6", "title": "\u95a2\u897f\u88fd\u7cd6"}, {"url": "https://ja.wikipedia.org/wiki/\u5927\u6771\u88fd\u7cd6", "sentence": "<p><b>\u5927\u6771\u88fd\u7cd6\u682a\u5f0f\u4f1a\u793e</b>\uff08\u3060\u3044\u3068\u3046\u305b\u3044\u3068\u3046\u3001\u82f1\u6587\u540d\u79f0<i>DAITO SEITO CO.,LTD.</i>\uff09\u306f\u3001\u300e<b>\u30af\u30ed\u30fc\u30d0\u30fc\u5370</b>\u300f\u306e\u30d6\u30e9\u30f3\u30c9\u3067\u7802\u7cd6\u7b49\u3092\u88fd\u9020\u8ca9\u58f2\u3057\u3066\u3044\u308b\u72ec\u7acb\u7cfb\u306e\u88fd\u7cd6\u4f1a\u793e\u30022006\u5e74\u73fe\u5728\u306f\u751f\u7523\u3092\u4ed6\u88fd\u7cd6\u4f1a\u793e\u3068\u306e\u5408\u5f01\u306e\u65b0\u6771\u65e5\u672c\u88fd\u7cd6\u3001\u95a2\u897f\u88fd\u7cd6\u306b\u59d4\u8a17\u3057\u3066\u3044\u308b\u3002</p>", "imurl": "N/A", "name": "\u5927\u6771\u88fd\u7cd6", "title": "\u5927\u6771\u88fd\u7cd6"}, {"url": "https://ja.wikipedia.org/wiki/\u5869\u6c34\u6e2f\u7cbe\u7cd6", "sentence": "<p><b>\u5869\u6c34\u6e2f\u7cbe\u7cd6\u682a\u5f0f\u4f1a\u793e</b>\uff08\u3048\u3093\u3059\u3044\u3053\u3046\u305b\u3044\u3068\u3046\uff09\u306f\u3001\u7802\u7cd6\u306e\u88fd\u9020\u8ca9\u58f2\u3092\u884c\u3046\u88fd\u7cd6\u4f1a\u793e\u3002</p>", "imurl": "https://upload.wikimedia.org/wikipedia/commons/thumb/0/02/Yensuiko_sugar_mill.jpg/250px-Yensuiko_sugar_mill.jpg", "name": "\u5869\u6c34\u6e2f\u7cbe\u7cd6", "title": "\u5869\u6c34\u6e2f\u7cbe\u7cd6"}, {"url": "https://ja.wikipedia.org/wiki/\u660e\u6cbb\u30db\u30fc\u30eb\u30c7\u30a3\u30f3\u30b0\u30b9", "title": "\u660e\u6cbb\u30db\u30fc\u30eb\u30c7\u30a3\u30f3\u30b0\u30b9", "name": "info", "sentence": "\u660e\u83d3\u3068\u660e\u4e73\u306f\u3001\u3068\u3082\u306b\u65e7\u30fb\u660e\u6cbb\u88fd\u7cd6\uff08\u305d\u306e\u5f8c\u7d4c\u55b6\u518d\u5efa\u306e\u904e\u7a0b\u3067<span id='entity'>\u65b0\u65e7\u5206\u96e2</span>\u306b\u3088\u308a\u65b0\u4f1a\u793e\u306b\u79fb\u884c\u3057\u3001\u65e7\u30fb\u5927\u65e5\u672c\u88fd\u7cd6\u3068\u5408\u4f75\u3057\u3066\u73fe\u5728\u306f<span id='entity'>\u5927\u65e5\u672c\u660e\u6cbb\u88fd\u7cd6</span>\uff09\u304b\u3089\u6d3e\u751f\u3057\u305f\u4f01\u696d\u3068\u3044\u3046\u3053\u3068\u3082\u3042\u308a\u3001\u660e\u4e73\u306f\u72ec\u81ea\u30ed\u30b4\u3092\u63a1\u7528\u3059\u308b\u307e\u3067\u306f\u660e\u83d3\u3068\u540c\u3058\u30ed\u30b4\u3067\u3042\u3063\u305f\u307b\u304b\u3001\u5546\u54c1\u306e<span id = 'relation'>\u5171\u540c\u958b\u767a</span>\u306a\u3069\u3092\u624b\u639b\u3051\u3066\u3044\u305f"}, {"url": "https://ja.wikipedia.org/wiki/\u65b0\u65e7\u5206\u96e2", "sentence": "<p><b>\u65b0\u65e7\u5206\u96e2</b>\uff08\u3057\u3093\u304d\u3085\u3046\u3076\u3093\u308a\uff09\u306f\u3001\u4f01\u696d\u304c\u7d4c\u55b6\u7834\u7dbb\u3042\u308b\u3044\u306f\u305d\u308c\u306b\u8fd1\u3044\u72b6\u614b\u306b\u9665\u3063\u305f\u969b\u306b\u3001\u305d\u306e\u4f01\u696d\u304c\u884c\u3063\u3066\u3044\u305f\u4e8b\u696d\u3092\u7d99\u7d9a\u3055\u305b\u5b9f\u8cea\u7684\u306a\u7d4c\u55b6\u518d\u5efa\u3092\u3081\u3056\u3059\u305f\u3081\u306b\u884c\u308f\u308c\u308b\u624b\u6bb5\u306e\u3072\u3068\u3064\u3067\u3042\u308b\u3002\u5546\u6cd5\u4e0a\u306b\u304a\u3044\u3066\u306f\u300c\u4f01\u696d\u5206\u5272\u300d\u3068\u300c\u4e8b\u696d\u8b72\u6e21\u300d\u306b\u5f53\u3066\u306f\u307e\u308b\u304c\u3001\u65e7\u6cd5\u4eba\u306e\u50b5\u52d9\u6574\u7406\u3068\u65b0\u6cd5\u4eba\u306b\u3088\u308b\u4e8b\u696d\u306e\u7d99\u7d9a\u3092\u305d\u306e\u76ee\u7684\u3068\u3059\u308b\u3082\u306e\u306b\u3064\u3044\u3066\u3001\u4ed6\u306e\u30b1\u30fc\u30b9\u3068\u533a\u5225\u3057\u3066\u3053\u3046\u547c\u3070\u308c\u308b\u3053\u3068\u304c\u591a\u3044\u3002\u4f1a\u793e\u5206\u5272\u3082\u53c2\u7167\u306e\u3053\u3068\u3002</p>", "imurl": "N/A", "name": "\u65b0\u65e7\u5206\u96e2", "title": "\u65b0\u65e7\u5206\u96e2"}, {"url": "https://ja.wikipedia.org/wiki/\u660e\u6cbb\u30db\u30fc\u30eb\u30c7\u30a3\u30f3\u30b0\u30b9", "sentence": "<p><b>\u660e\u6cbb\u30db\u30fc\u30eb\u30c7\u30a3\u30f3\u30b0\u30b9\u682a\u5f0f\u4f1a\u793e</b>\uff08\u3081\u3044\u3058\u30db\u30fc\u30eb\u30c7\u30a3\u30f3\u30b0\u30b9\uff09\u306f\u3001\u65e5\u672c\u306e\u98df\u54c1\u5927\u624b\u4f01\u696d\u306e\u660e\u6cbb\u88fd\u83d3\uff08\u4ee5\u4e0b\u300c\u660e\u83d3\u300d\u3068\u3059\u308b\uff09\u3068\u660e\u6cbb\u4e73\u696d\uff08\u4ee5\u4e0b\u300c\u660e\u4e73\u300d\u3068\u3059\u308b\uff09\u304c\u30012009\u5e744\u67081\u65e5\u4ed8\u3067\u682a\u5f0f\u79fb\u8ee2\u306b\u3088\u308a\u8a2d\u7acb\u3057\u305f\u7d14\u7c8b\u6301\u682a\u4f1a\u793e\u3002\u30b0\u30eb\u30fc\u30d7\u898f\u6a21\u3067\u5473\u306e\u7d20\u3068\u540c\u898f\u6a21\u306e\u4f01\u696d\u3068\u306a\u308b\u3002</p>", "imurl": "https://upload.wikimedia.org/wikipedia/commons/thumb/2/29/Meiji_Holdings_headquarters.jpg/187px-Meiji_Holdings_headquarters.jpg", "name": "\u660e\u6cbb\u30db\u30fc\u30eb\u30c7\u30a3\u30f3\u30b0\u30b9", "title": "\u660e\u6cbb\u30db\u30fc\u30eb\u30c7\u30a3\u30f3\u30b0\u30b9"}], "links": [{"source": 0, "target": 1, "value": 20}, {"source": 1, "target": 2, "value": 20}, {"source": 1, "target": 3, "value": 20}, {"source": 1, "target": 4, "value": 20}, {"source": 0, "target": 5, "value": 20}, {"source": 5, "target": 6, "value": 20}, {"source": 0, "target": 7, "value": 20}, {"source": 7, "target": 2, "value": 20}, {"source": 0, "target": 8, "value": 20}, {"source": 8, "target": 9, "value": 20}, {"source": 0, "target": 10, "value": 20}, {"source": 10, "target": 11, "value": 20}, {"source": 10, "target": 12, "value": 20}, {"source": 10, "target": 13, "value": 20}, {"source": 0, "target": 14, "value": 20}, {"source": 14, "target": 15, "value": 20}, {"source": 14, "target": 16, "value": 20}]}