{"nodes": [{"url": "https://ja.wikipedia.org/wiki/\u5ddd\u6751\u6e4a", "sentence": "<p><b>\u5ddd\u6751 \u6e4a</b>\uff08\u304b\u308f\u3080\u3089 \u307f\u306a\u3068\u30011951\u5e742\u670823\u65e5 - \uff09\u306f\u3001\u65e5\u672c\u306e\u6587\u82b8\u8a55\u8ad6\u5bb6\u3001\u6cd5\u653f\u5927\u5b66\u56fd\u969b\u6587\u5316\u5b66\u90e8\u6559\u6388\u3002</p>", "imurl": "N/A", "name": "\u5ddd\u6751\u6e4a", "title": "\u5ddd\u6751\u6e4a"}, {"url": "https://ja.wikipedia.org/wiki/\u6c60\u7530\u6d69\u58eb", "title": "\u6c60\u7530\u6d69\u58eb", "name": "info", "sentence": "\u300e\u6b7b\u5211\u6587\u5b66\u3092\u8aad\u3080\u300f<span id='person'>\u5ddd\u6751\u6e4a</span><span id = 'relation'>\u5171\u8457</span> \u30a4\u30f3\u30d1\u30af\u30c8\u51fa\u7248\u4f1a\u30002005"}, {"url": "https://ja.wikipedia.org/wiki/\u6c60\u7530\u6d69\u58eb", "sentence": "<p><b>\u6c60\u7530 \u6d69\u58eb</b>\uff08\u3044\u3051\u3060 \u3072\u308d\u3057\u30011940\u5e746\u670820\u65e5 - \uff09\u306f\u30c9\u30a4\u30c4\u6587\u5b66\u8005\u3001\u8a55\u8ad6\u5bb6\u3001\u4eac\u90fd\u5927\u5b66\u540d\u8a89\u6559\u6388\u3002</p>", "imurl": "N/A", "name": "\u6c60\u7530\u6d69\u58eb", "title": "\u6c60\u7530\u6d69\u58eb"}], "links": [{"source": 0, "target": 1, "value": 20}, {"source": 1, "target": 2, "value": 20}]}