{"nodes": [{"url": "https://ja.wikipedia.org/wiki/\u677e\u7551\u5f37", "sentence": "<p><br />\n<b>\u677e\u7551 \u5f37</b>\uff08\u307e\u3064\u306f\u305f \u3064\u3088\u3057\u30011961\u5e748\u670810\u65e5 - \uff09\u306f\u3001\u65e5\u672c\u306e\u5efa\u7bc9\u5bb6\u3002\u798f\u5ca1\u770c\u51fa\u8eab\u3002</p>", "imurl": "N/A", "name": "\u677e\u7551\u5f37", "title": "\u677e\u7551\u5f37"}, {"url": "https://ja.wikipedia.org/wiki/\u677e\u7551\u5f37", "title": "\u677e\u7551\u5f37", "name": "info", "sentence": " \u300e<span id='person'>\u30b8\u30e5\u30bc\u30c3\u30da\u30fb\u30c6\u30e9\u30fc\u30cb</span>\u3001\u6642\u4ee3\u3092\u99c6\u3051\u629c\u3051\u305f\u5efa\u7bc9\u300f\uff081998\u5e74\u3001<span id = 'relation'>\u5171\u8457</span>\u3001INAX\u51fa\u7248\uff09"}, {"url": "https://ja.wikipedia.org/wiki/\u30b8\u30e5\u30bc\u30c3\u30da\u30fb\u30c6\u30e9\u30fc\u30cb", "sentence": "<p><b>\u30b8\u30e5\u30bc\u30c3\u30da\u30fb\u30c6\u30e9\u30fc\u30cb</b>\uff08<b>Giuseppe Terragni</b>\u30011904\u5e744\u670818\u65e5 - 1943\u5e747\u670819\u65e5\uff09\u306f\u30a4\u30bf\u30ea\u30a2\u306e\u30e2\u30c0\u30cb\u30b9\u30c8\u306e\u5efa\u7bc9\u5bb6\u3001\u90fd\u5e02\u8a08\u753b\u5bb6\u3002\u5408\u7406\u4e3b\u7fa9\u5efa\u7bc9\u3092\u4ee3\u8868\u3059\u308b\u5efa\u7bc9\u5bb6\u3067\u3042\u3063\u305f\u3002</p>", "imurl": "N/A", "name": "\u30b8\u30e5\u30bc\u30c3\u30da\u30fb\u30c6\u30e9\u30fc\u30cb", "title": "\u30b8\u30e5\u30bc\u30c3\u30da\u30fb\u30c6\u30e9\u30fc\u30cb"}], "links": [{"source": 0, "target": 1, "value": 20}, {"source": 1, "target": 2, "value": 20}]}