{"nodes": [{"url": "https://ja.wikipedia.org/wiki/\u6c34\u5143\u3086\u3046\u306a", "sentence": "<p><b>\u6c34\u5143 \u3086\u3046\u306a</b>\uff08\u307f\u305a\u3082\u3068 \u3086\u3046\u306a\u30011983\u5e748\u670831\u65e5 - \uff09\u306f\u3001\u65e5\u672c\u306eAV\u5973\u512a\u3001\u30b9\u30c8\u30ea\u30c3\u30d1\u30fc\u3001\u5973\u512a\u3002\u682a\u5f0f\u4f1a\u793e\u30d3\u30e5\u30fc\u30b9\u30bf\u30a4\u30eb\u30ba\u30a8\u30f3\u30bf\u30fc\u30c6\u30a4\u30e1\u30f3\u30c8\u6240\u5c5e\u3002</p>", "imurl": "N/A", "name": "\u6c34\u5143\u3086\u3046\u306a", "title": "\u6c34\u5143\u3086\u3046\u306a"}, {"url": "https://ja.wikipedia.org/wiki/Nao.", "title": "Nao.", "name": "info", "sentence": " THE BEST OF CAST SUPER STARS\u2606FANTASTIC\u5927\u4e71\u4ea4 \uff084\u670819\u65e5\u3001kira\u2606kira\uff09<span id = 'relation'>\u5171\u6f14</span>:<span id='person'>\u6c34\u5143\u3086\u3046\u306a</span>\u3001<span id='person'>\u897f\u91ce\u7fd4</span>\u3001<span id='person'>\u5c0f\u6fa4\u30de\u30ea\u30a2</span>"}, {"url": "https://ja.wikipedia.org/wiki/\u5c0f\u6fa4\u30de\u30ea\u30a2", "sentence": "<p><b>\u5c0f\u6fa4 \u30de\u30ea\u30a2</b>\uff08\u304a\u3056\u308f \u30de\u30ea\u30a2\u30011986\u5e741\u67088\u65e5 - \uff09\u306f\u5317\u6d77\u9053\u51fa\u8eab\u306e\u5143AV\u5973\u512a\u3001\u30b9\u30c8\u30ea\u30c3\u30d1\u30fc\u3002\u30c6\u30a3\u30fc\u30d1\u30ef\u30fc\u30ba\uff08TPJ\uff09\u6240\u5c5e\u3002</p>", "imurl": "N/A", "name": "\u5c0f\u6fa4\u30de\u30ea\u30a2", "title": "\u5c0f\u6fa4\u30de\u30ea\u30a2"}, {"url": "https://ja.wikipedia.org/wiki/\u897f\u91ce\u7fd4", "sentence": "<p><b>\u897f\u91ce \u7fd4</b>\uff08\u306b\u3057\u306e \u3057\u3087\u3046\u30011985\u5e746\u670829\u65e5 - \uff09\u306f\u3001\u65e5\u672c\u306eAV\u5973\u512a\u3001\u30bf\u30ec\u30f3\u30c8\u3002\u682a\u5f0f\u4f1a\u793e\u30d7\u30e9\u30a4\u30e0\u30a8\u30fc\u30b8\u30a7\u30f3\u30b7\u30fc\u6240\u5c5e\u3002</p>", "imurl": "N/A", "name": "\u897f\u91ce\u7fd4", "title": "\u897f\u91ce\u7fd4"}, {"url": "https://ja.wikipedia.org/wiki/\u6c34\u5143\u3086\u3046\u306a", "title": "\u6c34\u5143\u3086\u3046\u306a", "name": "info", "sentence": " \u5c0f\u6ca2\u83dc\u7a42\u3068\u6c34\u5143\u3086\u3046\u306a\u306e\u30c0\u30d6\u30eb\u30c9\u30ea\u30fc\u30e0\u3000\u30b9\u30da\u30b7\u30e3\u30eb\uff088\u670819\u65e5\u3001\u30ec\u30a2\u30eb\u30fb\u30ef\u30fc\u30af\u30b9\uff09<span id = 'relation'>\u5171\u6f14</span>:<span id='person'>\u5c0f\u6ca2\u83dc\u7a42</span>"}, {"url": "https://ja.wikipedia.org/wiki/\u5c0f\u6ca2\u83dc\u7a42", "sentence": "<p><b>\u5c0f\u6ca2 \u83dc\u7a42</b>\uff08\u304a\u3056\u308f \u306a\u307b\u30011983\u5e741\u670826\u65e5 - \uff09\u306f\u3001\u65b0\u6f5f\u770c\u9577\u5ca1\u5e02\u51fa\u8eab\u306eAV\u5973\u512a\u3002</p>", "imurl": "N/A", "name": "\u5c0f\u6ca2\u83dc\u7a42", "title": "\u5c0f\u6ca2\u83dc\u7a42"}, {"url": "https://ja.wikipedia.org/wiki/\u6c34\u5143\u3086\u3046\u306a", "title": "\u6c34\u5143\u3086\u3046\u306a", "name": "info", "sentence": " \u8d85\u7d76\u54c1\u30dc\u30c7\u30a3\u30fcSPECIAL\uff083\u67081\u65e5\u3001MOODYZ\uff09<span id = 'relation'>\u5171\u6f14</span>:<span id='person'>\u5cf0\u306a\u3086\u304b</span>\u3001<span id='person'>\u5983\u4e43\u3072\u304b\u308a</span>\u3001<span id='person'>@YOU</span>"}, {"url": "https://ja.wikipedia.org/wiki/@YOU", "sentence": "<p><b>@YOU</b>\uff08\u3042\u3063\u3068\u3086\u3046\u30011986\u5e748\u670825\u65e5 - \uff09\u306f\u3001\u65e5\u672c\u306e\u5143AV\u5973\u512a\u3001\u5143\u30b9\u30c8\u30ea\u30c3\u30d1\u30fc\u3002\u6771\u4eac\u90fd\u51fa\u8eab\u3002\u30a2\u30af\u30b7\u30b9\u30d7\u30ed\u30e2\u30fc\u30b7\u30e7\u30f3\u6240\u5c5e\u3002</p>", "imurl": "N/A", "name": "@YOU", "title": "@YOU"}, {"url": "https://ja.wikipedia.org/wiki/\u5983\u4e43\u3072\u304b\u308a", "sentence": "<p><b>\u5983\u4e43 \u3072\u304b\u308a</b>\uff08\u3072\u306e \u3072\u304b\u308a\u30011986\u5e743\u67087\u65e5 - \uff09\u306f\u3001\u65e5\u672c\u306e\u5143AV\u5973\u512a\u3001\u5143\u30b9\u30c8\u30ea\u30c3\u30d1\u30fc\u3002\u682a\u5f0f\u4f1a\u793e\u30d3\u30e5\u30fc\u30b9\u30bf\u30a4\u30eb\u30ba\u30a8\u30f3\u30bf\u30fc\u30c6\u30a4\u30e1\u30f3\u30c8\u6240\u5c5e\u3002</p>", "imurl": "N/A", "name": "\u5983\u4e43\u3072\u304b\u308a", "title": "\u5983\u4e43\u3072\u304b\u308a"}, {"url": "https://ja.wikipedia.org/wiki/\u5cf0\u306a\u3086\u304b", "sentence": "<p><b>\u5cf0 \u306a\u3086\u304b</b>\uff08\u307f\u306d \u306a\u3086\u304b\u30011984\u5e749\u670829\u65e5 - \uff09\u306f\u3001\u5c90\u961c\u770c\u51fa\u8eab\u306e\u6f2b\u753b\u5bb6\u3001\u30e9\u30a4\u30bf\u30fc\u3002\u5143AV\u5973\u512a\u3067\u3042\u308b\u3002\u30ef\u30bf\u30ca\u30d9\u30a8\u30f3\u30bf\u30fc\u30c6\u30a4\u30f3\u30e1\u30f3\u30c8\u6240\u5c5e\u3002</p>", "imurl": "N/A", "name": "\u5cf0\u306a\u3086\u304b", "title": "\u5cf0\u306a\u3086\u304b"}, {"url": "https://ja.wikipedia.org/wiki/\u6c34\u5143\u3086\u3046\u306a", "title": "\u6c34\u5143\u3086\u3046\u306a", "name": "info", "sentence": " \u96c6\u56e3\u30dd\u30eb\u30c1\u30aa\u5927\u4e71\u4ea46\u6642\u9593\uff086\u67081\u65e5\u3001MOODYZ\uff09<span id = 'relation'>\u5171\u6f14</span>:<span id='person'>\u5927\u6ca2\u4f51\u9999</span>\u3001<span id='person'>\u53cb\u7530\u771f\u5e0c</span>\u3001<span id='person'>\u4e43\u4e9c</span>\u3001<span id='person'>\u8fbb\u3055\u304d</span>"}, {"url": "https://ja.wikipedia.org/wiki/\u6676\u30a8\u30ea\u30fc", "sentence": "<p><b>\u6676 \u30a8\u30ea\u30fc</b>\uff08\u3042\u304d\u3089 \u3048\u308a\u30fc\u30011986\u5e741\u670825\u65e5- \uff09\u306f\u3001\u65e5\u672c\u306eAV\u5973\u512a\u3001AV\u76e3\u7763\u3001\u5199\u771f\u5bb6\u3002\u6771\u4eac\u90fd\u51fa\u8eab\u3002</p>", "imurl": "N/A", "name": "\u6676\u30a8\u30ea\u30fc", "title": "\u6676\u30a8\u30ea\u30fc"}, {"url": "https://ja.wikipedia.org/wiki/\u53cb\u7530\u771f\u5e0c", "sentence": "<p><b>\u53cb\u7530 \u771f\u5e0c</b>\uff08\u3068\u3082\u3060 \u307e\u304d\u30011972\u5e748\u670820\u65e5 - \uff09\u306f\u3001\u65e5\u672c\u306e\u5143AV\u5973\u512a\u3002</p>", "imurl": "N/A", "name": "\u53cb\u7530\u771f\u5e0c", "title": "\u53cb\u7530\u771f\u5e0c"}, {"url": "https://ja.wikipedia.org/wiki/\u8fbb\u3055\u304d", "sentence": "<p><b>\u8fbb \u3055\u304d</b>\uff08\u3064\u3058 \u3055\u304d\u30011988\u5e748\u67089\u65e5 - \uff09\u306f\u3001\u65e5\u672c\u306eAV\u5973\u512a\u3001\u5143\u30b9\u30c8\u30ea\u30c3\u30d1\u30fc\u3002\u9752\u68ee\u770c\u51fa\u8eab\u3002\u8eab\u9577:160cm \u3001\u30b9\u30ea\u30fc\u30b5\u30a4\u30ba:B90\uff08G\u30ab\u30c3\u30d7\uff09\u30fbW61\u30fbH92\u3002</p>", "imurl": "N/A", "name": "\u8fbb\u3055\u304d", "title": "\u8fbb\u3055\u304d"}, {"url": "https://ja.wikipedia.org/wiki/\u4e43\u4e9c", "sentence": "<p><b>\u4e43\u4e9c</b>\uff08\u306e\u3042\u30011984\u5e741\u670812\u65e5 - \uff09\u306f\u3001\u65e5\u672c\u306eAV\u5973\u512a\u3002\u65b0\u65e5\u672c\u30d7\u30ed\u30b8\u30a7\u30af\u30c8\u6240\u5c5e\u3002</p>", "imurl": "N/A", "name": "\u4e43\u4e9c", "title": "\u4e43\u4e9c"}, {"url": "https://ja.wikipedia.org/wiki/\u6c34\u5143\u3086\u3046\u306a", "title": "\u6c34\u5143\u3086\u3046\u306a", "name": "info", "sentence": " \u65b0\u5974\u96b7\u5cf6 \u7b2c\u516d\u7ae0 \u666e\u901a\u306e\u751f\u6d3b\u304c\u3057\u305f\u304b\u3063\u305f\u2026\uff088\u67087\u65e5\u3001\u30a2\u30bf\u30c3\u30ab\u30fc\u30ba\uff09<span id = 'relation'>\u5171\u6f14</span>:<span id='person'>\u9752\u6728\u73b2</span>\u3001<span id='person'>\u9df9\u5bae\u308a\u3087\u3046</span>"}, {"url": "https://ja.wikipedia.org/wiki/\u9752\u6728\u73b2", "sentence": "<p><b>\u9752\u6728 \u73b2</b>\uff08\u3042\u304a\u304d \u308c\u3044\u30011984\u5e747\u670811\u65e5 - \uff09\u306f\u3001\u6771\u4eac\u90fd\u51fa\u8eab\u306e\u3001\u65e5\u672c\u306eAV\u5973\u512a\u3002</p>", "imurl": "N/A", "name": "\u9752\u6728\u73b2", "title": "\u9752\u6728\u73b2"}, {"url": "https://ja.wikipedia.org/wiki/\u9df9\u5bae\u308a\u3087\u3046", "sentence": "<p><b>\u9df9\u5bae \u308a\u3087\u3046</b>\uff08\u305f\u304b\u307f\u3084 \u308a\u3087\u3046\u30011982\u5e7411\u670821\u65e5 - \uff09\u306f\u3001\u65e5\u672c\u306eAV\u5973\u512a\u3002</p>", "imurl": "N/A", "name": "\u9df9\u5bae\u308a\u3087\u3046", "title": "\u9df9\u5bae\u308a\u3087\u3046"}, {"url": "https://ja.wikipedia.org/wiki/\u6c34\u5143\u3086\u3046\u306a", "title": "\u6c34\u5143\u3086\u3046\u306a", "name": "info", "sentence": " \u5974\u96b7\u57ce5\uff0812\u67087\u65e5\u3001\u30a2\u30bf\u30c3\u30ab\u30fc\u30ba\u3001ATTACKERS RBD-176\uff09<span id = 'relation'>\u5171\u6f14</span>:<span id='person'>\u59eb\u54b2\u308a\u308a\u3042</span>\u3001<span id='person'>\u7267\u672c\u5343\u5e78</span>\u3001MAYA"}, {"url": "https://ja.wikipedia.org/wiki/\u7267\u672c\u5343\u5e78", "sentence": "<p><b>\u7267\u672c \u5343\u5e78</b>\uff08\u307e\u304d\u3082\u3068 \u3061\u3086\u304d\u30011970\u5e748\u670826\u65e5 - \uff09\u306f\u3001\u65e5\u672c\u306eAV\u5973\u512a\u3001\u30b9\u30c8\u30ea\u30c3\u30d1\u30fc\u3002\u5e83\u5cf6\u770c\u51fa\u8eab\u3002</p>", "imurl": "N/A", "name": "\u7267\u672c\u5343\u5e78", "title": "\u7267\u672c\u5343\u5e78"}, {"url": "https://ja.wikipedia.org/wiki/\u59eb\u54b2\u308a\u308a\u3042", "sentence": "<p><b>\u59eb\u54b2 \u308a\u308a\u3042</b>\uff08\u3072\u3081\u3055\u304d \u308a\u308a\u3042\u30011985\u5e7410\u670810\u65e5 - \uff09\u306f\u3001\u65e5\u672c\u306eAV\u5973\u512a\u3002\u30a8\u30a4\u30c8\u30de\u30f3\u6240\u5c5e\u3002</p>", "imurl": "N/A", "name": "\u59eb\u54b2\u308a\u308a\u3042", "title": "\u59eb\u54b2\u308a\u308a\u3042"}, {"url": "https://ja.wikipedia.org/wiki/\u6c34\u5143\u3086\u3046\u306a", "title": "\u6c34\u5143\u3086\u3046\u306a", "name": "info", "sentence": " \u304f\u30ce\u4e00\u62f7\u554f\u51cc\u8fb15\uff086\u67087\u65e5\u3001\u30a2\u30bf\u30c3\u30ab\u30fc\u30ba\uff09<span id = 'relation'>\u5171\u6f14</span>:<span id='person'>\u3042\u3059\u304b\u4f0a\u592e</span>"}, {"url": "https://ja.wikipedia.org/wiki/\u3042\u3059\u304b\u4f0a\u592e", "sentence": "<p><b>\u3042\u3059\u304b \u4f0a\u592e</b>\uff08\u3042\u3059\u304b \u3044\u304a\u30011987\u5e7412\u670810\u65e5 - \uff09\u306f\u3001\u65e5\u672c\u306eAV\u5973\u512a\u3002</p>", "imurl": "N/A", "name": "\u3042\u3059\u304b\u4f0a\u592e", "title": "\u3042\u3059\u304b\u4f0a\u592e"}, {"url": "https://ja.wikipedia.org/wiki/\u6c34\u5143\u3086\u3046\u306a", "title": "\u6c34\u5143\u3086\u3046\u306a", "name": "info", "sentence": " \u82e5\u59bb\u306a\u3076\u308a \u611b\u6b32\u306e\u60b6\u3048\uff082006\u5e747\u67085\u65e5\u3001\u30d3\u30fc\u30a8\u30e0\u30c9\u30c3\u30c8\u30b9\u30ea\u30fc\uff09<span id = 'relation'>\u5171\u6f14</span>:<span id='person'>\u4eca\u91ce\u7531\u611b</span>"}, {"url": "https://ja.wikipedia.org/wiki/\u4eca\u91ce\u7531\u611b", "sentence": "<p><b>\u4eca\u91ce \u7531\u611b</b>\uff08\u3044\u307e\u306e \u3086\u3081\u30011985\u5e743\u67087\u65e5 - \uff09\u306f\u3001\u65e5\u672c\u306e\u5143AV\u5973\u512a\u3002\u6771\u4eac\u90fd\u51fa\u8eab\u3002\u30a4\u30aa\u30f3\u30d7\u30ed\u30e2\u30fc\u30b7\u30e7\u30f3\u306b\u6240\u5c5e\u3057\u3066\u3044\u305f\u3002</p>", "imurl": "N/A", "name": "\u4eca\u91ce\u7531\u611b", "title": "\u4eca\u91ce\u7531\u611b"}, {"url": "https://ja.wikipedia.org/wiki/\u6c34\u5143\u3086\u3046\u306a", "title": "\u6c34\u5143\u3086\u3046\u306a", "name": "info", "sentence": " \u4eba\u59bb\u3065\u304f\u3057 \u7dcf\u96c6\u7de8\uff082007\u5e743\u670828\u65e5\u3001\u30d3\u30fc\u30a8\u30e0\u30c9\u30c3\u30c8\u30b9\u30ea\u30fc\uff09<span id = 'relation'>\u5171\u6f14</span>:<span id='person'>\u6ca2\u7530\u9e97\u5948</span>"}, {"url": "https://ja.wikipedia.org/wiki/\u6ca2\u7530\u9e97\u5948", "sentence": "<p><b>\u6ca2\u7530 \u9e97\u5948</b>\uff08\u3055\u308f\u3060 \u308c\u3044\u306a\u300110\u67083\u65e5 - \uff09\u306f\u3001\u6771\u4eac\u90fd\u51fa\u8eab\u306e\u5b9f\u696d\u5bb6\u30fb\u5973\u512a\u30fbAV\u5973\u512a\u3002\u6240\u5c5e\u4e8b\u52d9\u6240\u306f\u30a2\u30ea\u30e5\u30fc\u30eb\u3002</p>", "imurl": "N/A", "name": "\u6ca2\u7530\u9e97\u5948", "title": "\u6ca2\u7530\u9e97\u5948"}, {"url": "https://ja.wikipedia.org/wiki/\u6c34\u5143\u3086\u3046\u306a", "title": "\u6c34\u5143\u3086\u3046\u306a", "name": "info", "sentence": " \u5996\u7f8e\u4f1d\u5947\u3000\u65b0\u8aac\u3000\u7261\u4e39\u706f\u7bed\u3000\u58f1 - \u3053\u306e\u4e16\u306e\u679c\u3066\uff082009\u5e74\uff09<span id = 'relation'>\u5171\u6f14</span>:<span id='person'>\u685c\u4e95\u307e\u308a</span>\u3001<span id='person'>\u5927\u6c5f\u671d\u7f8e</span>"}, {"url": "https://ja.wikipedia.org/wiki/\u685c\u4e95\u307e\u308a", "sentence": "<p><b>\u685c\u4e95 \u307e\u308a</b>\uff08\u3055\u304f\u3089\u3044 \u307e\u308a\u30011985\u5e745\u67089\u65e5 - \uff09\u306f\u3001\u65e5\u672c\u306e\u5143\u30b0\u30e9\u30d3\u30a2\u30a2\u30a4\u30c9\u30eb\u3001\u5973\u512a\u3001\u30bf\u30ec\u30f3\u30c8\u3002\u5343\u8449\u770c\u51fa\u8eab\u3002\u304b\u3064\u3066\u306e\u6240\u5c5e\u4e8b\u52d9\u6240\u306f\u30a8\u30cc\u30a2\u30f3\u30c9\u30a8\u30b9\u30d7\u30ed\u30e2\u30fc\u30b7\u30e7\u30f3\u3002</p>", "imurl": "N/A", "name": "\u685c\u4e95\u307e\u308a", "title": "\u685c\u4e95\u307e\u308a"}, {"url": "https://ja.wikipedia.org/wiki/\u5927\u6c5f\u671d\u7f8e", "sentence": "<p><b>\u5927\u6c5f \u671d\u7f8e</b>\uff08\u304a\u304a\u3048 \u3068\u3082\u307f\u30011989\u5e746\u670815\u65e5 - \uff09\u306f\u3001\u65e5\u672c\u306e\u5973\u512a\u3001\u5143\u30a2\u30a4\u30c9\u30eb\u3002\u6771\u4eac\u90fd\u51fa\u8eab\u3002\u5973\u6027\u30a2\u30a4\u30c9\u30eb\u30b0\u30eb\u30fc\u30d7AKB48\u304a\u3088\u3073DokiDoki\u2606\u30c9\u30ea\u30fc\u30e0\u30ad\u30e3\u30f3\u30d1\u30b9\u306e\u5143\u30e1\u30f3\u30d0\u30fc\u3002</p>", "imurl": "N/A", "name": "\u5927\u6c5f\u671d\u7f8e", "title": "\u5927\u6c5f\u671d\u7f8e"}, {"url": "https://ja.wikipedia.org/wiki/\u5982\u6708\u30ab\u30ec\u30f3", "title": "\u5982\u6708\u30ab\u30ec\u30f3", "name": "info", "sentence": " \u30d7\u30ec\u30df\u30a2\u30e0\u30fb\u30d3\u30e5\u30fc\u30c6\u30a3\u30fc\uff087\u67087\u65e5\u3001\u30d7\u30ec\u30df\u30a2\u30e0\uff09<span id = 'relation'>\u5171\u6f14</span>:<span id='person'>\u6c34\u5143\u3086\u3046\u306a</span>"}, {"url": "https://ja.wikipedia.org/wiki/\u5982\u6708\u30ab\u30ec\u30f3", "sentence": "<p><b>\u5982\u6708 \u30ab\u30ec\u30f3</b>\uff08\u304d\u3055\u3089\u304e \u30ab\u30ec\u30f3\u30011981\u5e743\u670826\u65e5 - \uff09\u306f\u3001\u65e5\u672c\u306e\u5143AV\u5973\u512a\u3002</p>", "imurl": "N/A", "name": "\u5982\u6708\u30ab\u30ec\u30f3", "title": "\u5982\u6708\u30ab\u30ec\u30f3"}, {"url": "https://ja.wikipedia.org/wiki/\u4e43\u4e9c", "title": "\u4e43\u4e9c", "name": "info", "sentence": " \u96c6\u56e3\u30dd\u30eb\u30c1\u30aa\u5927\u4e71\u4ea46\u6642\u9593 (6\u67081\u65e5\u3001MOODYZ)<span id = 'relation'>\u5171\u6f14</span>:<span id='person'>\u6c34\u5143\u3086\u3046\u306a</span>\u3001\u6676\u30a8\u30ea\u30fc\u3001\u53cb\u7530\u771f\u5e0c\u3001<span id='person'>\u8fbb\u3055\u304d</span>"}, {"url": "https://ja.wikipedia.org/wiki/\u5c0f\u6ca2\u83dc\u7a42", "title": "\u5c0f\u6ca2\u83dc\u7a42", "name": "info", "sentence": " \u5c0f\u6ca2\u83dc\u7a42\u3068\u6c34\u5143\u3086\u3046\u306a\u306e\u30c0\u30d6\u30eb\u30c9\u30ea\u30fc\u30e0 \u30b9\u30da\u30b7\u30e3\u30eb\uff088\u670819\u65e5\u3001\u30ec\u30a2\u30eb\u30fb\u30ef\u30fc\u30af\u30b9\uff09\u2026<span id = 'relation'>\u5171\u6f14</span>\uff1a<span id='person'>\u6c34\u5143\u3086\u3046\u306a</span>"}, {"url": "https://ja.wikipedia.org/wiki/\u5cf0\u306a\u3086\u304b", "title": "\u5cf0\u306a\u3086\u304b", "name": "info", "sentence": " \u8d85\u7d76\u54c1\u30dc\u30c7\u30a3\u30fcSPECIAL\uff083\u67081\u65e5\u3001MOODYZ\uff09<span id = 'relation'>\u5171\u6f14</span>:<span id='person'>\u6c34\u5143\u3086\u3046\u306a</span>\u3001<span id='person'>\u5983\u4e43\u3072\u304b\u308a</span>\u3001<span id='person'>@YOU</span>"}, {"url": "https://ja.wikipedia.org/wiki/\u897f\u91ce\u7fd4", "title": "\u897f\u91ce\u7fd4", "name": "info", "sentence": " THE BEST OF CAST SUPER STARS\u2606FANTASTIC\u5927\u4e71\u4ea4\uff084\u670819\u65e5\u3001kira\u2606kira SPECIAL\uff09<span id = 'relation'>\u5171\u6f14</span>:<span id='person'>\u6c34\u5143\u3086\u3046\u306a</span>\u3001<span id='person'>\u5c0f\u6fa4\u30de\u30ea\u30a2</span>\u3001nao."}, {"url": "https://ja.wikipedia.org/wiki/\u9752\u6728\u73b2", "title": "\u9752\u6728\u73b2", "name": "info", "sentence": " \u65b0\u5974\u96b7\u5cf6 \u7b2c\u516d\u7ae0 \u666e\u901a\u306e\u751f\u6d3b\u304c\u3057\u305f\u304b\u3063\u305f\u2026 (2009\u5e748\u67087\u65e5\u3001\u30a2\u30bf\u30c3\u30ab\u30fc\u30ba)<span id = 'relation'>\u5171\u6f14</span>:<span id='person'>\u6c34\u5143\u3086\u3046\u306a</span>\u3001<span id='person'>\u9df9\u5bae\u308a\u3087\u3046</span>"}, {"url": "https://ja.wikipedia.org/wiki/\u9752\u6728\u73b2", "title": "\u9752\u6728\u73b2", "name": "info", "sentence": " \u63a5\u543b\u3068\u30ec\u30ba\u3068\u4e71\u4ea4SPECIAL (2011\u5e742\u670825\u65e5\u3001\u7f8e)<span id = 'relation'>\u5171\u6f14</span>:<span id='person'>\u6c34\u5143\u3086\u3046\u306a</span>\u3001<span id='person'>\u4e9c\u5e0c\u83dc</span>\u3001\u9df9\u5bae\u308a\u3087\u3046"}, {"url": "https://ja.wikipedia.org/wiki/\u4e9c\u5e0c\u83dc", "sentence": "<p><b>\u4e9c\u5e0c\u83dc</b>\uff08\u3042\u304d\u306a\u30011987\u5e7412\u67084\u65e5 - \uff09\u306f\u3001\u65e5\u672c\u306eAV\u5973\u512a\u3002\u30c1\u30fc\u30ba\u30d0\u30fc\u30ac\u30fc\u6240\u5c5e\u3002</p>", "imurl": "N/A", "name": "\u4e9c\u5e0c\u83dc", "title": "\u4e9c\u5e0c\u83dc"}, {"url": "https://ja.wikipedia.org/wiki/@YOU", "title": "@YOU", "name": "info", "sentence": " \u8d85\u7d76\u54c1\u30dc\u30c7\u30a3\u30fcSPECIAL (3\u67081\u65e5\u3001MOODYZ)<span id = 'relation'>\u5171\u6f14</span>:<span id='person'>\u5cf0\u306a\u3086\u304b</span>\u3001<span id='person'>\u6c34\u5143\u3086\u3046\u306a</span>\u3001<span id='person'>\u5983\u4e43\u3072\u304b\u308a</span>"}, {"url": "https://ja.wikipedia.org/wiki/\u6676\u30a8\u30ea\u30fc", "title": "\u6676\u30a8\u30ea\u30fc", "name": "info", "sentence": " \u96c6\u56e3\u30dd\u30eb\u30c1\u30aa\u5927\u4e71\u4ea46\u6642\u9593\uff086\u67081\u65e5\u3001MOODYZ\uff09<span id = 'relation'>\u5171\u6f14</span>:<span id='person'>\u6c34\u5143\u3086\u3046\u306a</span>\u3001<span id='person'>\u53cb\u7530\u771f\u5e0c</span>\u3001\u4e43\u4e9c\u3001\u8fbb\u3055\u304d"}, {"url": "https://ja.wikipedia.org/wiki/\u6676\u30a8\u30ea\u30fc", "title": "\u6676\u30a8\u30ea\u30fc", "name": "info", "sentence": " \u96c6\u56e3\u30dd\u30eb\u30c1\u30aa\u5927\u4e71\u4ea46\u6642\u9593\uff086\u67081\u65e5\u3001MOODYZ\uff09<span id = 'relation'>\u5171\u6f14</span>:<span id='person'>\u6c34\u5143\u3086\u3046\u306a</span>\u3001\u53cb\u7530\u771f\u5e0c\u3001\u4e43\u4e9c\u3001\u8fbb\u3055\u304d"}, {"url": "https://ja.wikipedia.org/wiki/\u5983\u4e43\u3072\u304b\u308a", "title": "\u5983\u4e43\u3072\u304b\u308a", "name": "info", "sentence": " \u8d85\u7d76\u54c1\u30dc\u30c7\u30a3\u30fcSPECIAL (3\u67081\u65e5\u3001MOODYZ)<span id = 'relation'>\u5171\u6f14</span>:<span id='person'>\u5cf0\u306a\u3086\u304b</span>\u3001<span id='person'>\u6c34\u5143\u3086\u3046\u306a</span>\u3001<span id='person'>@YOU</span>"}, {"url": "https://ja.wikipedia.org/wiki/\u3042\u3059\u304b\u4f0a\u592e", "title": "\u3042\u3059\u304b\u4f0a\u592e", "name": "info", "sentence": " \u304f\u30ce\u4e00\u62f7\u554f\u51cc\u8fb15\u2026\uff086\u67087\u65e5\u3001\u30a2\u30bf\u30c3\u30ab\u30fc\u30ba\uff09<span id = 'relation'>\u5171\u6f14</span>\uff1a<span id='person'>\u6c34\u5143\u3086\u3046\u306a</span>"}, {"url": "https://ja.wikipedia.org/wiki/\u59eb\u54b2\u308a\u308a\u3042", "title": "\u59eb\u54b2\u308a\u308a\u3042", "name": "info", "sentence": " \u5974\u96b7\u57ce5(12\u67087\u65e5\u3001\u30a2\u30bf\u30c3\u30ab\u30fc\u30ba)\u2026<span id = 'relation'>\u5171\u6f14</span>:<span id='person'>\u6c34\u5143\u3086\u3046\u306a</span>\u3001<span id='person'>\u7267\u672c\u5343\u5e78</span>\u3001MAYA"}], "links": [{"source": 0, "target": 1, "value": 20}, {"source": 1, "target": 2, "value": 20}, {"source": 1, "target": 3, "value": 20}, {"source": 0, "target": 4, "value": 20}, {"source": 4, "target": 5, "value": 20}, {"source": 0, "target": 6, "value": 20}, {"source": 6, "target": 7, "value": 20}, {"source": 6, "target": 8, "value": 20}, {"source": 6, "target": 9, "value": 20}, {"source": 0, "target": 10, "value": 20}, {"source": 10, "target": 11, "value": 20}, {"source": 10, "target": 12, "value": 20}, {"source": 10, "target": 13, "value": 20}, {"source": 10, "target": 14, "value": 20}, {"source": 0, "target": 15, "value": 20}, {"source": 15, "target": 16, "value": 20}, {"source": 15, "target": 17, "value": 20}, {"source": 0, "target": 18, "value": 20}, {"source": 18, "target": 19, "value": 20}, {"source": 18, "target": 20, "value": 20}, {"source": 0, "target": 21, "value": 20}, {"source": 21, "target": 22, "value": 20}, {"source": 0, "target": 23, "value": 20}, {"source": 23, "target": 24, "value": 20}, {"source": 0, "target": 25, "value": 20}, {"source": 25, "target": 26, "value": 20}, {"source": 0, "target": 27, "value": 20}, {"source": 27, "target": 28, "value": 20}, {"source": 27, "target": 29, "value": 20}, {"source": 0, "target": 30, "value": 20}, {"source": 30, "target": 31, "value": 20}, {"source": 0, "target": 32, "value": 20}, {"source": 32, "target": 13, "value": 20}, {"source": 32, "target": 14, "value": 20}, {"source": 0, "target": 33, "value": 20}, {"source": 33, "target": 5, "value": 20}, {"source": 0, "target": 34, "value": 20}, {"source": 34, "target": 7, "value": 20}, {"source": 34, "target": 8, "value": 20}, {"source": 34, "target": 9, "value": 20}, {"source": 0, "target": 35, "value": 20}, {"source": 35, "target": 2, "value": 20}, {"source": 35, "target": 3, "value": 20}, {"source": 0, "target": 36, "value": 20}, {"source": 36, "target": 16, "value": 20}, {"source": 36, "target": 17, "value": 20}, {"source": 0, "target": 37, "value": 20}, {"source": 37, "target": 16, "value": 20}, {"source": 37, "target": 38, "value": 20}, {"source": 0, "target": 39, "value": 20}, {"source": 39, "target": 8, "value": 20}, {"source": 39, "target": 7, "value": 20}, {"source": 39, "target": 9, "value": 20}, {"source": 0, "target": 40, "value": 20}, {"source": 40, "target": 12, "value": 20}, {"source": 40, "target": 11, "value": 20}, {"source": 0, "target": 41, "value": 20}, {"source": 41, "target": 11, "value": 20}, {"source": 0, "target": 42, "value": 20}, {"source": 42, "target": 7, "value": 20}, {"source": 42, "target": 8, "value": 20}, {"source": 42, "target": 9, "value": 20}, {"source": 0, "target": 43, "value": 20}, {"source": 43, "target": 22, "value": 20}, {"source": 0, "target": 44, "value": 20}, {"source": 44, "target": 19, "value": 20}, {"source": 44, "target": 20, "value": 20}]}