{"nodes": [{"url": "https://ja.wikipedia.org/wiki/\u6d25\u7530\u5bdb\u6cbb", "sentence": "<p><b>\u6d25\u7530 \u5bdb\u6cbb</b>\uff08\u3064\u3060 \u304b\u3093\u3058\u30011965\u5e748\u670827\u65e5 - \uff09\u306f\u3001\u65e5\u672c\u306e\u4ff3\u512a\u3002\u30e9\u30fb\u30bb\u30c3\u30c6\u6240\u5c5e\u3002</p>", "imurl": "N/A", "name": "\u6d25\u7530\u5bdb\u6cbb", "title": "\u6d25\u7530\u5bdb\u6cbb"}, {"url": "https://ja.wikipedia.org/wiki/\u570b\u6751\u96bc", "title": "\u570b\u6751\u96bc", "name": "info", "sentence": " BOSS\u30b3\u30fc\u30d2\u30fc \u300c\u30dc\u30b9\u30b8\u30e3\u30f3\u300d\u7bc7\uff081999\u5e7412\u67081\u65e5\u3088\u308a\u3001<span id='person'>\u6d25\u7530\u5bdb\u6cbb</span>\u3068<span id = 'relation'>\u5171\u6f14</span>\uff09\u2026\u4e0a\u53f8\u5f79"}, {"url": "https://ja.wikipedia.org/wiki/\u570b\u6751\u96bc", "sentence": "<p><b>\u570b\u6751 \u96bc</b>\uff08\u304f\u306b\u3080\u3089 \u3058\u3085\u3093\u30011955\u5e7411\u670816\u65e5 - \uff09\u306f\u3001\u65e5\u672c\u306e\u4ff3\u512a\u3002\u5927\u962a\u5e9c\u51fa\u8eab\u3002</p>", "imurl": "N/A", "name": "\u570b\u6751\u96bc", "title": "\u570b\u6751\u96bc"}, {"url": "https://ja.wikipedia.org/wiki/\u571f\u5c4b\u592a\u9cf3", "title": "\u571f\u5c4b\u592a\u9cf3", "name": "info", "sentence": "\u305d\u306e\u64ae\u5f71\u73fe\u5834\u3067<span id = 'relation'>\u5171\u6f14</span>\u8005\u306e<span id='person'>\u9999\u5ddd\u7167\u4e4b</span>\u30fb<span id='person'>\u6d25\u7530\u5bdb\u6cbb</span>\u3068\u4ea4\u6d41\u3057\u3001\u5f7c\u3089\u306e\u4ed5\u4e8b\u3076\u308a\u3092\u76ee\u306e\u5f53\u305f\u308a\u306b\u3057\u305f\u3053\u3068\u3067\u5973\u512a\u3078\u306e\u6c7a\u610f\u3092\u5f37\u3081\u308b<ref name=\"Kagawa\"></ref>"}, {"url": "https://ja.wikipedia.org/wiki/\u9999\u5ddd\u7167\u4e4b", "sentence": "<p><b>\u9999\u5ddd \u7167\u4e4b</b>\uff08\u304b\u304c\u308f \u3066\u308b\u3086\u304d\u3001\u672c\u540d\u540c\u3058\u30011965\u5e7412\u67087\u65e5 - \uff09\u306f\u3001\u65e5\u672c\u306e\u4ff3\u512a\u3001\u6b4c\u821e\u4f0e\u5f79\u8005\u3001\u53ca\u3073\u30dc\u30af\u30b7\u30f3\u30b0\u89e3\u8aac\u8005\u3002</p>", "imurl": "N/A", "name": "\u9999\u5ddd\u7167\u4e4b", "title": "\u9999\u5ddd\u7167\u4e4b"}, {"url": "https://ja.wikipedia.org/wiki/\u571f\u5c4b\u592a\u9cf3", "sentence": "<p><b>\u571f\u5c4b \u592a\u9cf3</b>\uff08\u3064\u3061\u3084 \u305f\u304a \u30011995\u5e742\u67083\u65e5 - \uff09\u306f\u3001\u65e5\u672c\u306e\u5973\u512a\u3001\u30d5\u30a1\u30c3\u30b7\u30e7\u30f3\u30e2\u30c7\u30eb\u3002</p>", "imurl": "N/A", "name": "\u571f\u5c4b\u592a\u9cf3", "title": "\u571f\u5c4b\u592a\u9cf3"}], "links": [{"source": 0, "target": 1, "value": 20}, {"source": 1, "target": 2, "value": 20}, {"source": 0, "target": 3, "value": 20}, {"source": 3, "target": 4, "value": 20}, {"source": 3, "target": 5, "value": 20}]}