{"nodes": [{"url": "https://ja.wikipedia.org/wiki/\u6df1\u6c5f\u5353\u6b21", "sentence": "<p><b>\u6df1\u6c5f \u5353\u6b21</b>\uff08\u3075\u304b\u3048 \u305f\u304f\u3058\u30011967\u5e7412\u67082\u65e5 - \uff09\u306f\u3001\u65e5\u672c\u306e\u4ff3\u512a\u3002\u6771\u4eac\u90fd\u4e16\u7530\u8c37\u533a\u51fa\u8eab\u3002\u8840\u6db2\u578b\u306fO\u578b\u3002</p>", "imurl": "N/A", "name": "\u6df1\u6c5f\u5353\u6b21", "title": "\u6df1\u6c5f\u5353\u6b21"}, {"url": "https://ja.wikipedia.org/wiki/\u6e21\u54f2\u4e5f", "title": "\u6e21\u54f2\u4e5f", "name": "info", "sentence": " \u65e5\u672c\u8208\u4e9c\u640d\u4fdd\uff1d\u8218\u3072\u308d\u3057\u3001\u795e\u7530\u6b63\u8f1d\u3001<span id='person'>\u6df1\u6c5f\u5353\u6b21</span>\u3068<span id = 'relation'>\u5171\u6f14</span>"}, {"url": "https://ja.wikipedia.org/wiki/\u6e21\u54f2\u4e5f", "sentence": "<p><b>\u6e21 \u54f2\u4e5f</b>\uff08\u308f\u305f\u308a \u3066\u3064\u3084\u30011941\u5e7412\u670828\u65e5 - \uff09\u306f\u3001\u65e5\u672c\u306e\u4ff3\u512a\u30fb\u6b4c\u624b\u3002\u5143\u30fb\u682a\u5f0f\u4f1a\u793e\u77f3\u539f\u30d7\u30ed\u30e2\u30fc\u30b7\u30e7\u30f3\u4ee3\u8868\u53d6\u7de0\u5f79\u793e\u9577\uff082011\u5e74\u9000\u4efb\uff09\u3002</p>", "imurl": "N/A", "name": "\u6e21\u54f2\u4e5f", "title": "\u6e21\u54f2\u4e5f"}, {"url": "https://ja.wikipedia.org/wiki/\u6df1\u6c5f\u5353\u6b21", "title": "\u6df1\u6c5f\u5353\u6b21", "name": "info", "sentence": "1992\u5e74\u3001\u30c6\u30ec\u30d3\u30c9\u30e9\u30de\u300e\u751f\u547d\u71c3\u3086\u300f\u3067<span id='person'>\u6e21\u54f2\u4e5f</span>\u3068<span id = 'relation'>\u5171\u6f14</span>\u3057\u3001\u3053\u308c\u3092\u6a5f\u306b\u77f3\u539f\u30d7\u30ed\u30e2\u30fc\u30b7\u30e7\u30f3\u306b\u79fb\u7c4d\u3057\u3001\u77f3\u539f\u8ecd\u56e3\u306e\u4e00\u54e1\u3068\u3057\u3066\u6d3b\u52d5\u3059\u308b"}], "links": [{"source": 0, "target": 1, "value": 20}, {"source": 1, "target": 2, "value": 20}, {"source": 0, "target": 3, "value": 20}, {"source": 3, "target": 2, "value": 20}]}