{"nodes": [{"url": "https://ja.wikipedia.org/wiki/\u7c73\u5ca1\u8aa0\u4e00", "sentence": "<p><b>\u7c73\u5ca1 \u8aa0\u4e00</b>\uff08\u3088\u306d\u304a\u304b \u305b\u3044\u3044\u3061\u3001\u672c\u540d\u540c\u3058\u30011958\u5e7410\u670819\u65e5-\uff09\u306f\u3001\u65e5\u672c\u306e\u30e9\u30b8\u30aaDJ\u30fb\u30ca\u30ec\u30fc\u30bf\u30fc\u30fb\u30df\u30e5\u30fc\u30b8\u30b7\u30e3\u30f3\u30fb\u30ed\u30fc\u30ab\u30eb\u30bf\u30ec\u30f3\u30c8\u30fb\u82b8\u80fd\u30d7\u30ed\u30e2\u30fc\u30bf\u30fc\u3067\u3042\u308b\u3002\u5317\u4e5d\u5dde\u5e02\u9580\u53f8\u533a\u51fa\u8eab\u3002\u8840\u6db2\u578bO\u578b\u3001\u3042\u3060\u540d\u306f<b>\u3044\u306e\u3057\u3057</b>\u3002</p>", "imurl": "N/A", "name": "\u7c73\u5ca1\u8aa0\u4e00", "title": "\u7c73\u5ca1\u8aa0\u4e00"}, {"url": "https://ja.wikipedia.org/wiki/\u6728\u539f\u53cb\u9999", "title": "\u6728\u539f\u53cb\u9999", "name": "info", "sentence": "<span id='person'>\u7c73\u5ca1\u8aa0\u4e00</span>\uff08\u30e9\u30b8\u2605\u30b4\u30f3\u3067<span id = 'relation'>\u5171\u6f14</span>\uff09"}, {"url": "https://ja.wikipedia.org/wiki/\u6728\u539f\u53cb\u9999", "sentence": "<p><b>\u6728\u539f \u53cb\u9999</b>\uff08\u304d\u306f\u3089 \u3086\u3046\u304b\u30011972\u5e74 - \uff09\u306f\u3001\u30d5\u30ea\u30fc\u30a2\u30ca\u30a6\u30f3\u30b5\u30fc\u3002\u4f50\u8cc0\u770c\u9e7f\u5cf6\u5e02\u51fa\u8eab\u3002\u5143\u592b\u306f\u4e5d\u5dde\u671d\u65e5\u653e\u9001\u30cb\u30e5\u30fc\u30b9\u30ad\u30e3\u30b9\u30bf\u30fc\u306e\u8fd1\u85e4\u9244\u592a\u90ce\u3002</p>", "imurl": "N/A", "name": "\u6728\u539f\u53cb\u9999", "title": "\u6728\u539f\u53cb\u9999"}], "links": [{"source": 0, "target": 1, "value": 20}, {"source": 1, "target": 2, "value": 20}]}