{"nodes": [{"url": "https://ja.wikipedia.org/wiki/\u8449\u5c71\u7531\u4f73", "sentence": "<p><b>\u8449\u5c71 \u7531\u4f73</b>\uff08\u306f\u3084\u307e \u3086\u304b\u30011988\u5e7411\u670827\u65e5 - \uff09\u306f\u3001\u65e5\u672c\u306eAV\u5973\u512a\u3002</p>", "imurl": "N/A", "name": "\u8449\u5c71\u7531\u4f73", "title": "\u8449\u5c71\u7531\u4f73"}, {"url": "https://ja.wikipedia.org/wiki/\u30e2\u30ab (AV\u5973\u512a)", "title": "\u30e2\u30ab (AV\u5973\u512a)", "name": "info", "sentence": " kira\u2606kira BLACK GAL SPECIAL \u304e\u3083\u308b\u306e\u308a\u2606\u30e4\u30ea\u30b3\u30f3SEX!\u30d0\u30b9\u306e\u65c5\uff089\u670819\u65e5\u3001kira\u2606kira\uff09<span id = 'relation'>\u5171\u6f14</span>:\u6cc9\u9ebb\u90a3\u3001RUMIKA\u3001<span id='person'>\u8449\u5c71\u7531\u4f73</span>\u3001<span id='person'>\u54c0\u5ddd\u308a\u3093</span>"}, {"url": "https://ja.wikipedia.org/wiki/\u54c0\u5ddd\u308a\u3093", "sentence": "<p><b>\u54c0\u5ddd \u308a\u3093</b>\uff08\u3042\u3044\u304b\u308f \u308a\u3093\uff09\u306f\u3001\u65e5\u672c\u306eAV\u5973\u512a\u3002</p>", "imurl": "N/A", "name": "\u54c0\u5ddd\u308a\u3093", "title": "\u54c0\u5ddd\u308a\u3093"}, {"url": "https://ja.wikipedia.org/wiki/\u30e2\u30ab (AV\u5973\u512a)", "sentence": "<p><b>\u30e2\u30ab\u30fbMOKA\u30fberika</b>\uff08\u3048\u308a\u304b\u30011988\u5e747\u67087\u65e5 - \uff09\u306f\u3001\u65e5\u672c\u306eAV\u5973\u512a\u3002</p>", "imurl": "N/A", "name": "\u30e2\u30ab (AV\u5973\u512a)", "title": "\u30e2\u30ab (AV\u5973\u512a)"}], "links": [{"source": 0, "target": 1, "value": 20}, {"source": 1, "target": 2, "value": 20}, {"source": 1, "target": 3, "value": 20}]}