{"nodes": [{"url": "https://ja.wikipedia.org/wiki/\u85e4\u5009\u308c\u3044\u307f", "sentence": "<p><b>\u85e4\u5009 \u308c\u3044\u307f</b>\uff08\u3075\u3058\u304f\u3089 \u308c\u3044\u307f\u30011987\u5e742\u67089\u65e5 - \uff09\u306f\u3001\u65e5\u672c\u306eAV\u5973\u512a\u3002</p>", "imurl": "N/A", "name": "\u85e4\u5009\u308c\u3044\u307f", "title": "\u85e4\u5009\u308c\u3044\u307f"}, {"url": "https://ja.wikipedia.org/wiki/\u590f\u5ddd\u4e9c\u54b2", "title": "\u590f\u5ddd\u4e9c\u54b2", "name": "info", "sentence": " \u30ae\u30ea\u30ae\u30ea\u30e2\u30b6\u30a4\u30af \u7121\u9650\u7d76\u9802!\u6fc0\u30a4\u30ab\u30bb\u5927\u4e71\u4ea4\uff0812\u67087\u65e5\u3001\u30a8\u30b9\u30ef\u30f3\uff09<span id = 'relation'>\u5171\u6f14</span>:<span id='person'>\u85e4\u5009\u308c\u3044\u307f</span>"}, {"url": "https://ja.wikipedia.org/wiki/\u590f\u5ddd\u4e9c\u54b2", "sentence": "<p><b>\u590f\u5ddd \u4e9c\u54b2</b>\uff08\u306a\u3064\u304b\u308f \u3042\u3055\u304d\u30011987\u5e749\u670820\u65e5 - \uff09\u306f\u3001\u65e5\u672c\u306eAV\u5973\u512a\u3002\u30d7\u30e9\u30a4\u30e0\u30a8\u30fc\u30b8\u30a7\u30f3\u30b7\u30fc\u6240\u5c5e\u3002</p>", "imurl": "N/A", "name": "\u590f\u5ddd\u4e9c\u54b2", "title": "\u590f\u5ddd\u4e9c\u54b2"}, {"url": "https://ja.wikipedia.org/wiki/\u85e4\u5009\u308c\u3044\u307f", "title": "\u85e4\u5009\u308c\u3044\u307f", "name": "info", "sentence": " \u30ae\u30ea\u30ae\u30ea\u30e2\u30b6\u30a4\u30af \u7121\u9650\u7d76\u9802\uff01\u6fc0\u30a4\u30ab\u30bb\u5927\u4e71\u4ea4\uff082007\u5e7411\u67087\u65e5\u3001\u30a8\u30b9\u30ef\u30f3\uff09\u2026<span id = 'relation'>\u5171\u6f14</span>:<span id='person'>\u590f\u5ddd\u4e9c\u54b2</span>"}], "links": [{"source": 0, "target": 1, "value": 20}, {"source": 1, "target": 2, "value": 20}, {"source": 0, "target": 3, "value": 20}, {"source": 3, "target": 2, "value": 20}]}