{"nodes": [{"url": "https://ja.wikipedia.org/wiki/\u9577\u8c37\u5ddd\u7531\u7f8e", "sentence": "<p><b>\u9577\u8c37\u5ddd \u7531\u7f8e</b>\uff08\u306f\u305b\u304c\u308f \u3086\u307f\u30011980\u5e74 - \uff09\u306f\u3001\u65e5\u672c\u306e\u5143AV\u5973\u512a\u3002\u6771\u4eac\u90fd\u51fa\u8eab\u3002\u8840\u6db2\u578b:A\u578b\u3002</p>", "imurl": "N/A", "name": "\u9577\u8c37\u5ddd\u7531\u7f8e", "title": "\u9577\u8c37\u5ddd\u7531\u7f8e"}, {"url": "https://ja.wikipedia.org/wiki/\u661f\u91ce\u7460\u6d77", "title": "\u661f\u91ce\u7460\u6d77", "name": "info", "sentence": " \u75f4\u5973\u884c\u70ba\u306e\u865c\u306b\u306a\u3063\u305f\u79c1\u305f\u3061 OL\u8272\u60c5\u72c2\uff089\u67087\u65e5\u3001\u30cf\u30e0\u30ec\u30c3\u30c8\uff09<span id = 'relation'>\u5171\u6f14</span>:\u5409\u6fa4\u840c\u9999\u3001<span id='person'>\u9577\u8c37\u5ddd\u7531\u7f8e</span>\u3001\u897f\u6fa4\u9ebb\u91cc\u3001\u5185\u7530\u65e9\u7d00"}, {"url": "https://ja.wikipedia.org/wiki/\u661f\u91ce\u7460\u6d77", "sentence": "<p><b>\u661f\u91ce \u7460\u6d77</b>\uff08\u307b\u3057\u306e \u308b\u307f\u30011973\u5e742\u67087\u65e5 - \uff09\u306f\u3001\u795e\u5948\u5ddd\u770c\u51fa\u8eab\u306e\u5143AV\u5973\u512a\u3002</p>", "imurl": "N/A", "name": "\u661f\u91ce\u7460\u6d77", "title": "\u661f\u91ce\u7460\u6d77"}], "links": [{"source": 0, "target": 1, "value": 20}, {"source": 1, "target": 2, "value": 20}]}