{"nodes": [{"url": "https://ja.wikipedia.org/wiki/\u9ed2\u4e95\u6587\u592a\u90ce", "sentence": "<p><b>\u9ed2\u4e95\u6587\u592a\u90ce</b>\uff08\u304f\u308d\u3044\u3076\u3093\u305f\u308d\u3046\u30011963\u5e74 - \uff09\u306f\u3001\u65e5\u672c\u306e\u8ecd\u4e8b\u30a2\u30ca\u30ea\u30b9\u30c8\u3002\u798f\u5cf6\u770c\u3044\u308f\u304d\u5e02\u751f\u307e\u308c\u3002</p>", "imurl": "N/A", "name": "\u9ed2\u4e95\u6587\u592a\u90ce", "title": "\u9ed2\u4e95\u6587\u592a\u90ce"}, {"url": "https://ja.wikipedia.org/wiki/\u9ed2\u4e95\u6587\u592a\u90ce", "title": "\u9ed2\u4e95\u6587\u592a\u90ce", "name": "info", "sentence": " \u300e\u751f\u7269\u5175\u5668\u30c6\u30ed\u300f\uff08\u5b9d\u5cf6\u793e\u65b0\u66f8\u30012002\u5e74\uff09 ISBN 4-7966-2567-4\u3000\u3000<span id='person'>\u6751\u4e0a\u548c\u5df3</span>\u3068\u306e<span id = 'relation'>\u5171\u8457</span>"}, {"url": "https://ja.wikipedia.org/wiki/\u6751\u4e0a\u548c\u5df3", "sentence": "<p><b>\u6751\u4e0a \u548c\u5df3</b>\uff08\u3080\u3089\u304b\u307f \u304b\u305a\u307f\u30011969\u5e74 - \uff09\u306f\u3001\u65e5\u672c\u306e\u30d5\u30ea\u30fc\u30b8\u30e3\u30fc\u30ca\u30ea\u30b9\u30c8\u3002\u5bae\u57ce\u770c\u4e98\u7406\u90e1\u4e98\u7406\u753a\u51fa\u8eab\u3002\u4ed9\u53f0\u7b2c\u4e00\u9ad8\u7b49\u5b66\u6821\u3001\u4e2d\u592e\u5927\u5b66\u7406\u5de5\u5b66\u90e8\u5352\u696d\u3002</p>", "imurl": "N/A", "name": "\u6751\u4e0a\u548c\u5df3", "title": "\u6751\u4e0a\u548c\u5df3"}], "links": [{"source": 0, "target": 1, "value": 20}, {"source": 1, "target": 2, "value": 20}]}